[
  {
    "id": "457838a93f97361ca8509d67bc2781f66798f284",
    "fecha": "2022-01-01",
    "comercio": "KUESKI PAY",
    "giro_comercio": "AUTOFINANCIAMIENTOS - SERVICIOS FINANCIEROS",
    "tipo_venta": "digital",
    "monto": 75.6
  },
  {
    "id": "457838a93f97361ca8509d67bc2781f66798f284",
    "fecha": "2022-01-04",
    "comercio": "UBER EATS",
    "giro_comercio": "TRASLADOS - FLETES, (SERVICIOS DE MENSAJERIA)",
    "tipo_venta": "digital",
    "monto": 17.59
  },
  {
    "id": "457838a93f97361ca8509d67bc2781f66798f284",
    "fecha": "2022-01-04",
    "comercio": "AMAZON",
    "giro_comercio": "COMERCIOS ELECTRONICOS (VTAS POR INTERNET)",
    "tipo_venta": "digital",
    "monto": 17.36
  },
  {
    "id": "457838a93f97361ca8509d67bc2781f66798f284",
    "fecha": "2022-01-04",
    "comercio": "OXXO",
    "giro_comercio": "TIENDAS DE CONVENIENCIA, MINISUPER",
    "tipo_venta": "fisica",
    "monto": 17.47
  },
  {
    "id": "457838a93f97361ca8509d67bc2781f66798f284",
    "fecha": "2022-01-05",
    "comercio": "UBER EATS",
    "giro_comercio": "TRASLADOS - FLETES, (SERVICIOS DE MENSAJERIA)",
    "tipo_venta": "digital",
    "monto": 46.92
  },
  {
    "id": "457838a93f97361ca8509d67bc2781f66798f284",
    "fecha": "2022-01-05",
    "comercio": "AMAZON",
    "giro_comercio": "COMERCIOS ELECTRONICOS (VTAS POR INTERNET)",
    "tipo_venta": "digital",
    "monto": 17.82
  },
  {
    "id": "457838a93f97361ca8509d67bc2781f66798f284",
    "fecha": "2022-01-06",
    "comercio": "FARMACIAS GUADALAJARA",
    "giro_comercio": "DROGUERIAS, (FARMACIAS)",
    "tipo_venta": "fisica",
    "monto": 13.16
  },
  {
    "id": "457838a93f97361ca8509d67bc2781f66798f284",
    "fecha": "2022-01-06",
    "comercio": "UBER EATS",
    "giro_comercio": "TRASLADOS - FLETES, (SERVICIOS DE MENSAJERIA)",
    "tipo_venta": "digital",
    "monto": 47.19
  },
  {
    "id": "457838a93f97361ca8509d67bc2781f66798f284",
    "fecha": "2022-01-12",
    "comercio": "AMAZON",
    "giro_comercio": "COMERCIOS ELECTRONICOS (VTAS POR INTERNET)",
    "tipo_venta": "digital",
    "monto": 2.54
  },
  {
    "id": "457838a93f97361ca8509d67bc2781f66798f284",
    "fecha": "2022-01-12",
    "comercio": "AMAZON",
    "giro_comercio": "COMERCIOS ELECTRONICOS (VTAS POR INTERNET)",
    "tipo_venta": "digital",
    "monto": 51.9
  },
  {
    "id": "457838a93f97361ca8509d67bc2781f66798f284",
    "fecha": "2022-01-12",
    "comercio": "UBER EATS",
    "giro_comercio": "TRASLADOS - FLETES, (SERVICIOS DE MENSAJERIA)",
    "tipo_venta": "digital",
    "monto": 51.15
  },
  {
    "id": "457838a93f97361ca8509d67bc2781f66798f284",
    "fecha": "2022-01-12",
    "comercio": "KUESKI PAY",
    "giro_comercio": "AUTOFINANCIAMIENTOS - SERVICIOS FINANCIEROS",
    "tipo_venta": "digital",
    "monto": 85.71
  },
  {
    "id": "457838a93f97361ca8509d67bc2781f66798f284",
    "fecha": "2022-01-13",
    "comercio": "AMAZON",
    "giro_comercio": "COMERCIOS ELECTRONICOS (VTAS POR INTERNET)",
    "tipo_venta": "digital",
    "monto": 84.94
  },
  {
    "id": "457838a93f97361ca8509d67bc2781f66798f284",
    "fecha": "2022-01-14",
    "comercio": "OXXO",
    "giro_comercio": "TIENDAS DE CONVENIENCIA, MINISUPER",
    "tipo_venta": "fisica",
    "monto": 15.64
  },
  {
    "id": "457838a93f97361ca8509d67bc2781f66798f284",
    "fecha": "2022-01-16",
    "comercio": "AMAZON",
    "giro_comercio": "COMERCIOS ELECTRONICOS (VTAS POR INTERNET)",
    "tipo_venta": "digital",
    "monto": 115.58
  },
  {
    "id": "457838a93f97361ca8509d67bc2781f66798f284",
    "fecha": "2022-01-17",
    "comercio": "AMAZON",
    "giro_comercio": "COMERCIOS ELECTRONICOS (VTAS POR INTERNET)",
    "tipo_venta": "digital",
    "monto": 101.27
  },
  {
    "id": "457838a93f97361ca8509d67bc2781f66798f284",
    "fecha": "2022-01-19",
    "comercio": "SPOTIFY",
    "giro_comercio": "AGREGADOR",
    "tipo_venta": "digital",
    "monto": 23.1
  },
  {
    "id": "457838a93f97361ca8509d67bc2781f66798f284",
    "fecha": "2022-01-19",
    "comercio": "OXXO",
    "giro_comercio": "TIENDAS DE CONVENIENCIA, MINISUPER",
    "tipo_venta": "fisica",
    "monto": 9.89
  },
  {
    "id": "457838a93f97361ca8509d67bc2781f66798f284",
    "fecha": "2022-01-21",
    "comercio": "UBER EATS",
    "giro_comercio": "TRASLADOS - FLETES, (SERVICIOS DE MENSAJERIA)",
    "tipo_venta": "digital",
    "monto": 28.1
  },
  {
    "id": "457838a93f97361ca8509d67bc2781f66798f284",
    "fecha": "2022-01-21",
    "comercio": "UBER EATS",
    "giro_comercio": "TRASLADOS - FLETES, (SERVICIOS DE MENSAJERIA)",
    "tipo_venta": "digital",
    "monto": 43.57
  },
  {
    "id": "457838a93f97361ca8509d67bc2781f66798f284",
    "fecha": "2022-01-26",
    "comercio": "OXXO",
    "giro_comercio": "TIENDAS DE CONVENIENCIA, MINISUPER",
    "tipo_venta": "fisica",
    "monto": 7.48
  },
  {
    "id": "457838a93f97361ca8509d67bc2781f66798f284",
    "fecha": "2022-01-26",
    "comercio": "UBER EATS",
    "giro_comercio": "TRASLADOS - FLETES, (SERVICIOS DE MENSAJERIA)",
    "tipo_venta": "digital",
    "monto": 28.21
  },
  {
    "id": "457838a93f97361ca8509d67bc2781f66798f284",
    "fecha": "2022-01-27",
    "comercio": "UBER EATS",
    "giro_comercio": "TRASLADOS - FLETES, (SERVICIOS DE MENSAJERIA)",
    "tipo_venta": "digital",
    "monto": 20.5
  },
  {
    "id": "457838a93f97361ca8509d67bc2781f66798f284",
    "fecha": "2022-01-27",
    "comercio": "UBER EATS",
    "giro_comercio": "TRASLADOS - FLETES, (SERVICIOS DE MENSAJERIA)",
    "tipo_venta": "digital",
    "monto": 20.17
  },
  {
    "id": "457838a93f97361ca8509d67bc2781f66798f284",
    "fecha": "2022-01-28",
    "comercio": "FARMACIAS GUADALAJARA",
    "giro_comercio": "DROGUERIAS, (FARMACIAS)",
    "tipo_venta": "fisica",
    "monto": 44.73
  },
  {
    "id": "457838a93f97361ca8509d67bc2781f66798f284",
    "fecha": "2022-01-30",
    "comercio": "KUESKI PAY",
    "giro_comercio": "AUTOFINANCIAMIENTOS - SERVICIOS FINANCIEROS",
    "tipo_venta": "digital",
    "monto": 85.71
  },
  {
    "id": "457838a93f97361ca8509d67bc2781f66798f284",
    "fecha": "2022-02-02",
    "comercio": "AMAZON",
    "giro_comercio": "COMERCIOS ELECTRONICOS (VTAS POR INTERNET)",
    "tipo_venta": "digital",
    "monto": 43.76
  },
  {
    "id": "457838a93f97361ca8509d67bc2781f66798f284",
    "fecha": "2022-02-02",
    "comercio": "AMAZON",
    "giro_comercio": "COMERCIOS ELECTRONICOS (VTAS POR INTERNET)",
    "tipo_venta": "digital",
    "monto": 43.76
  },
  {
    "id": "457838a93f97361ca8509d67bc2781f66798f284",
    "fecha": "2022-02-02",
    "comercio": "AMAZON",
    "giro_comercio": "COMERCIOS ELECTRONICOS (VTAS POR INTERNET)",
    "tipo_venta": "digital",
    "monto": 63.31
  },
  {
    "id": "457838a93f97361ca8509d67bc2781f66798f284",
    "fecha": "2022-02-02",
    "comercio": "AMAZON",
    "giro_comercio": "COMERCIOS ELECTRONICOS (VTAS POR INTERNET)",
    "tipo_venta": "digital",
    "monto": 43.76
  },
  {
    "id": "457838a93f97361ca8509d67bc2781f66798f284",
    "fecha": "2022-02-02",
    "comercio": "UBER EATS",
    "giro_comercio": "TRASLADOS - FLETES, (SERVICIOS DE MENSAJERIA)",
    "tipo_venta": "digital",
    "monto": 16.84
  },
  {
    "id": "457838a93f97361ca8509d67bc2781f66798f284",
    "fecha": "2022-02-02",
    "comercio": "UBER EATS",
    "giro_comercio": "TRASLADOS - FLETES, (SERVICIOS DE MENSAJERIA)",
    "tipo_venta": "digital",
    "monto": 17.98
  },
  {
    "id": "457838a93f97361ca8509d67bc2781f66798f284",
    "fecha": "2022-02-02",
    "comercio": "UBER EATS",
    "giro_comercio": "TRASLADOS - FLETES, (SERVICIOS DE MENSAJERIA)",
    "tipo_venta": "digital",
    "monto": 23.25
  },
  {
    "id": "457838a93f97361ca8509d67bc2781f66798f284",
    "fecha": "2022-02-02",
    "comercio": "UBER EATS",
    "giro_comercio": "TRASLADOS - FLETES, (SERVICIOS DE MENSAJERIA)",
    "tipo_venta": "digital",
    "monto": 24.8
  },
  {
    "id": "457838a93f97361ca8509d67bc2781f66798f284",
    "fecha": "2022-02-03",
    "comercio": "AMAZON",
    "giro_comercio": "COMERCIOS ELECTRONICOS (VTAS POR INTERNET)",
    "tipo_venta": "digital",
    "monto": 63.31
  },
  {
    "id": "457838a93f97361ca8509d67bc2781f66798f284",
    "fecha": "2022-02-03",
    "comercio": "AMAZON",
    "giro_comercio": "COMERCIOS ELECTRONICOS (VTAS POR INTERNET)",
    "tipo_venta": "digital",
    "monto": 63.31
  },
  {
    "id": "457838a93f97361ca8509d67bc2781f66798f284",
    "fecha": "2022-02-03",
    "comercio": "AMAZON",
    "giro_comercio": "COMERCIOS ELECTRONICOS (VTAS POR INTERNET)",
    "tipo_venta": "digital",
    "monto": 63.31
  },
  {
    "id": "457838a93f97361ca8509d67bc2781f66798f284",
    "fecha": "2022-02-03",
    "comercio": "AMAZON",
    "giro_comercio": "COMERCIOS ELECTRONICOS (VTAS POR INTERNET)",
    "tipo_venta": "digital",
    "monto": 63.31
  },
  {
    "id": "457838a93f97361ca8509d67bc2781f66798f284",
    "fecha": "2022-02-03",
    "comercio": "UBER EATS",
    "giro_comercio": "TRASLADOS - FLETES, (SERVICIOS DE MENSAJERIA)",
    "tipo_venta": "digital",
    "monto": 29.36
  },
  {
    "id": "457838a93f97361ca8509d67bc2781f66798f284",
    "fecha": "2022-02-06",
    "comercio": "MERCADO PAGO",
    "giro_comercio": "COMERCIOS ELECTRONICOS (VTAS POR INTERNET)",
    "tipo_venta": "digital",
    "monto": 142.25
  },
  {
    "id": "457838a93f97361ca8509d67bc2781f66798f284",
    "fecha": "2022-02-09",
    "comercio": "UBER EATS",
    "giro_comercio": "TRASLADOS - FLETES, (SERVICIOS DE MENSAJERIA)",
    "tipo_venta": "digital",
    "monto": 15.13
  },
  {
    "id": "457838a93f97361ca8509d67bc2781f66798f284",
    "fecha": "2022-02-09",
    "comercio": "UBER EATS",
    "giro_comercio": "TRASLADOS - FLETES, (SERVICIOS DE MENSAJERIA)",
    "tipo_venta": "digital",
    "monto": 26.78
  },
  {
    "id": "457838a93f97361ca8509d67bc2781f66798f284",
    "fecha": "2022-02-10",
    "comercio": "UBER EATS",
    "giro_comercio": "TRASLADOS - FLETES, (SERVICIOS DE MENSAJERIA)",
    "tipo_venta": "digital",
    "monto": 20.17
  },
  {
    "id": "457838a93f97361ca8509d67bc2781f66798f284",
    "fecha": "2022-02-12",
    "comercio": "AMAZON",
    "giro_comercio": "COMERCIOS ELECTRONICOS (VTAS POR INTERNET)",
    "tipo_venta": "digital",
    "monto": 2.54
  },
  {
    "id": "457838a93f97361ca8509d67bc2781f66798f284",
    "fecha": "2022-02-12",
    "comercio": "AMAZON",
    "giro_comercio": "COMERCIOS ELECTRONICOS (VTAS POR INTERNET)",
    "tipo_venta": "digital",
    "monto": 32.87
  },
  {
    "id": "457838a93f97361ca8509d67bc2781f66798f284",
    "fecha": "2022-02-13",
    "comercio": "KUESKI PAY",
    "giro_comercio": "AUTOFINANCIAMIENTOS - SERVICIOS FINANCIEROS",
    "tipo_venta": "digital",
    "monto": 85.71
  },
  {
    "id": "457838a93f97361ca8509d67bc2781f66798f284",
    "fecha": "2022-02-13",
    "comercio": "FARMACIAS GUADALAJARA",
    "giro_comercio": "DROGUERIAS, (FARMACIAS)",
    "tipo_venta": "fisica",
    "monto": 59.35
  },
  {
    "id": "457838a93f97361ca8509d67bc2781f66798f284",
    "fecha": "2022-02-15",
    "comercio": "UBER EATS",
    "giro_comercio": "TRASLADOS - FLETES, (SERVICIOS DE MENSAJERIA)",
    "tipo_venta": "digital",
    "monto": 23.3
  },
  {
    "id": "457838a93f97361ca8509d67bc2781f66798f284",
    "fecha": "2022-02-16",
    "comercio": "OXXO",
    "giro_comercio": "TIENDAS DE CONVENIENCIA, MINISUPER",
    "tipo_venta": "fisica",
    "monto": 9.89
  },
  {
    "id": "457838a93f97361ca8509d67bc2781f66798f284",
    "fecha": "2022-02-17",
    "comercio": "7 ELEVEN",
    "giro_comercio": "TIENDAS DE CONVENIENCIA, MINISUPER",
    "tipo_venta": "fisica",
    "monto": 9.32
  },
  {
    "id": "457838a93f97361ca8509d67bc2781f66798f284",
    "fecha": "2022-02-17",
    "comercio": "STARBUCKS",
    "giro_comercio": "COMIDA RAPIDA",
    "tipo_venta": "fisica",
    "monto": 22.99
  },
  {
    "id": "457838a93f97361ca8509d67bc2781f66798f284",
    "fecha": "2022-02-18",
    "comercio": "CARLS JR",
    "giro_comercio": "COMIDA RAPIDA",
    "tipo_venta": "fisica",
    "monto": 8.74
  },
  {
    "id": "457838a93f97361ca8509d67bc2781f66798f284",
    "fecha": "2022-02-19",
    "comercio": "SPOTIFY",
    "giro_comercio": "AGREGADOR",
    "tipo_venta": "digital",
    "monto": 23.1
  },
  {
    "id": "457838a93f97361ca8509d67bc2781f66798f284",
    "fecha": "2022-02-23",
    "comercio": "UBER EATS",
    "giro_comercio": "TRASLADOS - FLETES, (SERVICIOS DE MENSAJERIA)",
    "tipo_venta": "digital",
    "monto": 25.25
  },
  {
    "id": "457838a93f97361ca8509d67bc2781f66798f284",
    "fecha": "2022-02-23",
    "comercio": "UBER EATS",
    "giro_comercio": "TRASLADOS - FLETES, (SERVICIOS DE MENSAJERIA)",
    "tipo_venta": "digital",
    "monto": 19.12
  },
  {
    "id": "457838a93f97361ca8509d67bc2781f66798f284",
    "fecha": "2022-02-24",
    "comercio": "OXXO",
    "giro_comercio": "TIENDAS DE CONVENIENCIA, MINISUPER",
    "tipo_venta": "fisica",
    "monto": 8.8
  },
  {
    "id": "457838a93f97361ca8509d67bc2781f66798f284",
    "fecha": "2022-02-24",
    "comercio": "KUESKI PAY",
    "giro_comercio": "AUTOFINANCIAMIENTOS - SERVICIOS FINANCIEROS",
    "tipo_venta": "digital",
    "monto": 85.71
  },
  {
    "id": "457838a93f97361ca8509d67bc2781f66798f284",
    "fecha": "2022-02-24",
    "comercio": "UBER EATS",
    "giro_comercio": "TRASLADOS - FLETES, (SERVICIOS DE MENSAJERIA)",
    "tipo_venta": "digital",
    "monto": 49.72
  },
  {
    "id": "457838a93f97361ca8509d67bc2781f66798f284",
    "fecha": "2022-03-06",
    "comercio": "AMAZON",
    "giro_comercio": "COMERCIOS ELECTRONICOS (VTAS POR INTERNET)",
    "tipo_venta": "digital",
    "monto": 47.34
  },
  {
    "id": "457838a93f97361ca8509d67bc2781f66798f284",
    "fecha": "2022-03-08",
    "comercio": "FARMACIAS GUADALAJARA",
    "giro_comercio": "DROGUERIAS, (FARMACIAS)",
    "tipo_venta": "fisica",
    "monto": 12.71
  },
  {
    "id": "457838a93f97361ca8509d67bc2781f66798f284",
    "fecha": "2022-03-09",
    "comercio": "OXXO",
    "giro_comercio": "TIENDAS DE CONVENIENCIA, MINISUPER",
    "tipo_venta": "fisica",
    "monto": 63.17
  },
  {
    "id": "457838a93f97361ca8509d67bc2781f66798f284",
    "fecha": "2022-03-11",
    "comercio": "FARMACIAS GUADALAJARA",
    "giro_comercio": "DROGUERIAS, (FARMACIAS)",
    "tipo_venta": "fisica",
    "monto": 10.57
  },
  {
    "id": "457838a93f97361ca8509d67bc2781f66798f284",
    "fecha": "2022-03-15",
    "comercio": "FARMACIAS DEL AHORRO",
    "giro_comercio": "DROGUERIAS, (FARMACIAS)",
    "tipo_venta": "fisica",
    "monto": 21.84
  },
  {
    "id": "457838a93f97361ca8509d67bc2781f66798f284",
    "fecha": "2022-03-16",
    "comercio": "OXXO",
    "giro_comercio": "TIENDAS DE CONVENIENCIA, MINISUPER",
    "tipo_venta": "fisica",
    "monto": 57.33
  },
  {
    "id": "457838a93f97361ca8509d67bc2781f66798f284",
    "fecha": "2022-03-19",
    "comercio": "UBER EATS",
    "giro_comercio": "TRASLADOS - FLETES, (SERVICIOS DE MENSAJERIA)",
    "tipo_venta": "digital",
    "monto": 17.04
  },
  {
    "id": "457838a93f97361ca8509d67bc2781f66798f284",
    "fecha": "2022-03-19",
    "comercio": "SPOTIFY",
    "giro_comercio": "AGREGADOR",
    "tipo_venta": "digital",
    "monto": 23.1
  },
  {
    "id": "457838a93f97361ca8509d67bc2781f66798f284",
    "fecha": "2022-03-20",
    "comercio": "OXXO",
    "giro_comercio": "TIENDAS DE CONVENIENCIA, MINISUPER",
    "tipo_venta": "fisica",
    "monto": 5.07
  },
  {
    "id": "457838a93f97361ca8509d67bc2781f66798f284",
    "fecha": "2022-03-22",
    "comercio": "UBER EATS",
    "giro_comercio": "TRASLADOS - FLETES, (SERVICIOS DE MENSAJERIA)",
    "tipo_venta": "digital",
    "monto": 31.37
  },
  {
    "id": "457838a93f97361ca8509d67bc2781f66798f284",
    "fecha": "2022-03-23",
    "comercio": "UBER EATS",
    "giro_comercio": "TRASLADOS - FLETES, (SERVICIOS DE MENSAJERIA)",
    "tipo_venta": "digital",
    "monto": 38.1
  },
  {
    "id": "457838a93f97361ca8509d67bc2781f66798f284",
    "fecha": "2022-03-27",
    "comercio": "UBER EATS",
    "giro_comercio": "TRASLADOS - FLETES, (SERVICIOS DE MENSAJERIA)",
    "tipo_venta": "digital",
    "monto": 57.18
  },
  {
    "id": "457838a93f97361ca8509d67bc2781f66798f284",
    "fecha": "2022-03-29",
    "comercio": "SORIANA",
    "giro_comercio": "AUTOSERVICIOS Y SUPERMERCADOS",
    "tipo_venta": "fisica",
    "monto": 12.79
  },
  {
    "id": "457838a93f97361ca8509d67bc2781f66798f284",
    "fecha": "2022-03-30",
    "comercio": "OXXO",
    "giro_comercio": "TIENDAS DE CONVENIENCIA, MINISUPER",
    "tipo_venta": "fisica",
    "monto": 30.92
  },
  {
    "id": "457838a93f97361ca8509d67bc2781f66798f284",
    "fecha": "2022-03-30",
    "comercio": "UBER EATS",
    "giro_comercio": "TRASLADOS - FLETES, (SERVICIOS DE MENSAJERIA)",
    "tipo_venta": "digital",
    "monto": 49.97
  },
  {
    "id": "457838a93f97361ca8509d67bc2781f66798f284",
    "fecha": "2022-04-03",
    "comercio": "OXXO",
    "giro_comercio": "TIENDAS DE CONVENIENCIA, MINISUPER",
    "tipo_venta": "fisica",
    "monto": 14.2
  },
  {
    "id": "457838a93f97361ca8509d67bc2781f66798f284",
    "fecha": "2022-04-05",
    "comercio": "OXXO",
    "giro_comercio": "TIENDAS DE CONVENIENCIA, MINISUPER",
    "tipo_venta": "fisica",
    "monto": 22.24
  },
  {
    "id": "457838a93f97361ca8509d67bc2781f66798f284",
    "fecha": "2022-04-06",
    "comercio": "OXXO",
    "giro_comercio": "TIENDAS DE CONVENIENCIA, MINISUPER",
    "tipo_venta": "fisica",
    "monto": 10.93
  },
  {
    "id": "457838a93f97361ca8509d67bc2781f66798f284",
    "fecha": "2022-04-09",
    "comercio": "FARMACIAS GUADALAJARA",
    "giro_comercio": "DROGUERIAS, (FARMACIAS)",
    "tipo_venta": "fisica",
    "monto": 29.02
  },
  {
    "id": "457838a93f97361ca8509d67bc2781f66798f284",
    "fecha": "2022-04-12",
    "comercio": "AMAZON",
    "giro_comercio": "COMERCIOS ELECTRONICOS (VTAS POR INTERNET)",
    "tipo_venta": "digital",
    "monto": 2.54
  },
  {
    "id": "457838a93f97361ca8509d67bc2781f66798f284",
    "fecha": "2022-04-12",
    "comercio": "AMAZON",
    "giro_comercio": "COMERCIOS ELECTRONICOS (VTAS POR INTERNET)",
    "tipo_venta": "digital",
    "monto": 85.28
  },
  {
    "id": "457838a93f97361ca8509d67bc2781f66798f284",
    "fecha": "2022-04-13",
    "comercio": "UBER EATS",
    "giro_comercio": "TRASLADOS - FLETES, (SERVICIOS DE MENSAJERIA)",
    "tipo_venta": "digital",
    "monto": 20.96
  },
  {
    "id": "457838a93f97361ca8509d67bc2781f66798f284",
    "fecha": "2022-04-13",
    "comercio": "UBER EATS",
    "giro_comercio": "TRASLADOS - FLETES, (SERVICIOS DE MENSAJERIA)",
    "tipo_venta": "digital",
    "monto": 47.02
  },
  {
    "id": "457838a93f97361ca8509d67bc2781f66798f284",
    "fecha": "2022-04-19",
    "comercio": "SPOTIFY",
    "giro_comercio": "AGREGADOR",
    "tipo_venta": "digital",
    "monto": 23.1
  },
  {
    "id": "457838a93f97361ca8509d67bc2781f66798f284",
    "fecha": "2022-04-19",
    "comercio": "HEB",
    "giro_comercio": "AUTOSERVICIOS Y SUPERMERCADOS",
    "tipo_venta": "fisica",
    "monto": 66.57
  },
  {
    "id": "457838a93f97361ca8509d67bc2781f66798f284",
    "fecha": "2022-04-21",
    "comercio": "UBER EATS",
    "giro_comercio": "TRASLADOS - FLETES, (SERVICIOS DE MENSAJERIA)",
    "tipo_venta": "digital",
    "monto": 49.08
  },
  {
    "id": "457838a93f97361ca8509d67bc2781f66798f284",
    "fecha": "2022-04-23",
    "comercio": "OXXO",
    "giro_comercio": "TIENDAS DE CONVENIENCIA, MINISUPER",
    "tipo_venta": "fisica",
    "monto": 17.47
  },
  {
    "id": "457838a93f97361ca8509d67bc2781f66798f284",
    "fecha": "2022-04-25",
    "comercio": "OXXO",
    "giro_comercio": "TIENDAS DE CONVENIENCIA, MINISUPER",
    "tipo_venta": "fisica",
    "monto": 22.18
  },
  {
    "id": "457838a93f97361ca8509d67bc2781f66798f284",
    "fecha": "2022-04-26",
    "comercio": "UBER EATS",
    "giro_comercio": "TRASLADOS - FLETES, (SERVICIOS DE MENSAJERIA)",
    "tipo_venta": "digital",
    "monto": 38.6
  },
  {
    "id": "457838a93f97361ca8509d67bc2781f66798f284",
    "fecha": "2022-04-26",
    "comercio": "OXXO",
    "giro_comercio": "TIENDAS DE CONVENIENCIA, MINISUPER",
    "tipo_venta": "fisica",
    "monto": 21.15
  },
  {
    "id": "457838a93f97361ca8509d67bc2781f66798f284",
    "fecha": "2022-04-30",
    "comercio": "UBER EATS",
    "giro_comercio": "TRASLADOS - FLETES, (SERVICIOS DE MENSAJERIA)",
    "tipo_venta": "digital",
    "monto": 11.73
  },
  {
    "id": "457838a93f97361ca8509d67bc2781f66798f284",
    "fecha": "2022-05-02",
    "comercio": "OXXO",
    "giro_comercio": "TIENDAS DE CONVENIENCIA, MINISUPER",
    "tipo_venta": "fisica",
    "monto": 17.01
  },
  {
    "id": "457838a93f97361ca8509d67bc2781f66798f284",
    "fecha": "2022-05-03",
    "comercio": "UBER EATS",
    "giro_comercio": "TRASLADOS - FLETES, (SERVICIOS DE MENSAJERIA)",
    "tipo_venta": "digital",
    "monto": 24.87
  },
  {
    "id": "457838a93f97361ca8509d67bc2781f66798f284",
    "fecha": "2022-05-03",
    "comercio": "OXXO",
    "giro_comercio": "TIENDAS DE CONVENIENCIA, MINISUPER",
    "tipo_venta": "fisica",
    "monto": 24.25
  },
  {
    "id": "457838a93f97361ca8509d67bc2781f66798f284",
    "fecha": "2022-05-05",
    "comercio": "UBER EATS",
    "giro_comercio": "TRASLADOS - FLETES, (SERVICIOS DE MENSAJERIA)",
    "tipo_venta": "digital",
    "monto": 49.36
  },
  {
    "id": "457838a93f97361ca8509d67bc2781f66798f284",
    "fecha": "2022-05-06",
    "comercio": "UBER EATS",
    "giro_comercio": "TRASLADOS - FLETES, (SERVICIOS DE MENSAJERIA)",
    "tipo_venta": "digital",
    "monto": 16.9
  },
  {
    "id": "457838a93f97361ca8509d67bc2781f66798f284",
    "fecha": "2022-05-10",
    "comercio": "OXXO",
    "giro_comercio": "TIENDAS DE CONVENIENCIA, MINISUPER",
    "tipo_venta": "fisica",
    "monto": 32.98
  },
  {
    "id": "457838a93f97361ca8509d67bc2781f66798f284",
    "fecha": "2022-05-12",
    "comercio": "UBER EATS",
    "giro_comercio": "TRASLADOS - FLETES, (SERVICIOS DE MENSAJERIA)",
    "tipo_venta": "digital",
    "monto": 69.35
  },
  {
    "id": "457838a93f97361ca8509d67bc2781f66798f284",
    "fecha": "2022-05-13",
    "comercio": "UBER EATS",
    "giro_comercio": "TRASLADOS - FLETES, (SERVICIOS DE MENSAJERIA)",
    "tipo_venta": "digital",
    "monto": 13.13
  },
  {
    "id": "457838a93f97361ca8509d67bc2781f66798f284",
    "fecha": "2022-05-16",
    "comercio": "OXXO",
    "giro_comercio": "TIENDAS DE CONVENIENCIA, MINISUPER",
    "tipo_venta": "fisica",
    "monto": 14.37
  },
  {
    "id": "457838a93f97361ca8509d67bc2781f66798f284",
    "fecha": "2022-05-18",
    "comercio": "AMAZON",
    "giro_comercio": "COMERCIOS ELECTRONICOS (VTAS POR INTERNET)",
    "tipo_venta": "digital",
    "monto": 2.54
  },
  {
    "id": "457838a93f97361ca8509d67bc2781f66798f284",
    "fecha": "2022-05-18",
    "comercio": "AMAZON",
    "giro_comercio": "COMERCIOS ELECTRONICOS (VTAS POR INTERNET)",
    "tipo_venta": "digital",
    "monto": 107.9
  },
  {
    "id": "457838a93f97361ca8509d67bc2781f66798f284",
    "fecha": "2022-05-19",
    "comercio": "UBER EATS",
    "giro_comercio": "TRASLADOS - FLETES, (SERVICIOS DE MENSAJERIA)",
    "tipo_venta": "digital",
    "monto": 69.1
  },
  {
    "id": "457838a93f97361ca8509d67bc2781f66798f284",
    "fecha": "2022-05-19",
    "comercio": "SPOTIFY",
    "giro_comercio": "AGREGADOR",
    "tipo_venta": "digital",
    "monto": 23.1
  },
  {
    "id": "457838a93f97361ca8509d67bc2781f66798f284",
    "fecha": "2022-05-23",
    "comercio": "FARMACIAS GUADALAJARA",
    "giro_comercio": "DROGUERIAS, (FARMACIAS)",
    "tipo_venta": "fisica",
    "monto": 50.56
  },
  {
    "id": "457838a93f97361ca8509d67bc2781f66798f284",
    "fecha": "2022-05-24",
    "comercio": "OXXO",
    "giro_comercio": "TIENDAS DE CONVENIENCIA, MINISUPER",
    "tipo_venta": "fisica",
    "monto": 25.97
  },
  {
    "id": "457838a93f97361ca8509d67bc2781f66798f284",
    "fecha": "2022-05-31",
    "comercio": "OXXO",
    "giro_comercio": "TIENDAS DE CONVENIENCIA, MINISUPER",
    "tipo_venta": "fisica",
    "monto": 32.41
  },
  {
    "id": "457838a93f97361ca8509d67bc2781f66798f284",
    "fecha": "2022-06-01",
    "comercio": "UBER EATS",
    "giro_comercio": "TRASLADOS - FLETES, (SERVICIOS DE MENSAJERIA)",
    "tipo_venta": "digital",
    "monto": 25.91
  },
  {
    "id": "457838a93f97361ca8509d67bc2781f66798f284",
    "fecha": "2022-06-05",
    "comercio": "OXXO",
    "giro_comercio": "TIENDAS DE CONVENIENCIA, MINISUPER",
    "tipo_venta": "fisica",
    "monto": 9.66
  },
  {
    "id": "457838a93f97361ca8509d67bc2781f66798f284",
    "fecha": "2022-06-06",
    "comercio": "UBER EATS",
    "giro_comercio": "TRASLADOS - FLETES, (SERVICIOS DE MENSAJERIA)",
    "tipo_venta": "digital",
    "monto": 25.91
  },
  {
    "id": "457838a93f97361ca8509d67bc2781f66798f284",
    "fecha": "2022-06-07",
    "comercio": "UBER EATS",
    "giro_comercio": "TRASLADOS - FLETES, (SERVICIOS DE MENSAJERIA)",
    "tipo_venta": "digital",
    "monto": 12.18
  },
  {
    "id": "457838a93f97361ca8509d67bc2781f66798f284",
    "fecha": "2022-06-07",
    "comercio": "OXXO",
    "giro_comercio": "TIENDAS DE CONVENIENCIA, MINISUPER",
    "tipo_venta": "fisica",
    "monto": 20.86
  },
  {
    "id": "457838a93f97361ca8509d67bc2781f66798f284",
    "fecha": "2022-06-09",
    "comercio": "UBER EATS",
    "giro_comercio": "AGREGADOR",
    "tipo_venta": "digital",
    "monto": 73.67
  },
  {
    "id": "457838a93f97361ca8509d67bc2781f66798f284",
    "fecha": "2022-06-13",
    "comercio": "UBER EATS",
    "giro_comercio": "TRASLADOS - FLETES, (SERVICIOS DE MENSAJERIA)",
    "tipo_venta": "digital",
    "monto": 28.0
  },
  {
    "id": "457838a93f97361ca8509d67bc2781f66798f284",
    "fecha": "2022-06-13",
    "comercio": "OXXO",
    "giro_comercio": "TIENDAS DE CONVENIENCIA, MINISUPER",
    "tipo_venta": "fisica",
    "monto": 12.53
  },
  {
    "id": "457838a93f97361ca8509d67bc2781f66798f284",
    "fecha": "2022-06-13",
    "comercio": "CINEPOLIS",
    "giro_comercio": "CINES, TEATROS",
    "tipo_venta": "fisica",
    "monto": 34.36
  },
  {
    "id": "457838a93f97361ca8509d67bc2781f66798f284",
    "fecha": "2022-06-15",
    "comercio": "UBER EATS",
    "giro_comercio": "AGREGADOR",
    "tipo_venta": "digital",
    "monto": 36.04
  },
  {
    "id": "457838a93f97361ca8509d67bc2781f66798f284",
    "fecha": "2022-06-15",
    "comercio": "DIDIFOOD",
    "giro_comercio": "COMIDA RAPIDA",
    "tipo_venta": "digital",
    "monto": 25.12
  },
  {
    "id": "457838a93f97361ca8509d67bc2781f66798f284",
    "fecha": "2022-06-16",
    "comercio": "APPLE",
    "giro_comercio": NaN,
    "tipo_venta": "fisica",
    "monto": 69.06
  },
  {
    "id": "457838a93f97361ca8509d67bc2781f66798f284",
    "fecha": "2022-06-16",
    "comercio": "UBER EATS",
    "giro_comercio": "AGREGADOR",
    "tipo_venta": "digital",
    "monto": 30.03
  },
  {
    "id": "457838a93f97361ca8509d67bc2781f66798f284",
    "fecha": "2022-06-17",
    "comercio": "OXXO",
    "giro_comercio": "TIENDAS DE CONVENIENCIA, MINISUPER",
    "tipo_venta": "fisica",
    "monto": 10.93
  },
  {
    "id": "457838a93f97361ca8509d67bc2781f66798f284",
    "fecha": "2022-06-17",
    "comercio": "OXXO",
    "giro_comercio": "TIENDAS DE CONVENIENCIA, MINISUPER",
    "tipo_venta": "fisica",
    "monto": 4.78
  },
  {
    "id": "457838a93f97361ca8509d67bc2781f66798f284",
    "fecha": "2022-06-18",
    "comercio": "OXXO",
    "giro_comercio": "TIENDAS DE CONVENIENCIA, MINISUPER",
    "tipo_venta": "fisica",
    "monto": 16.73
  },
  {
    "id": "457838a93f97361ca8509d67bc2781f66798f284",
    "fecha": "2022-06-19",
    "comercio": "SPOTIFY",
    "giro_comercio": "AGREGADOR",
    "tipo_venta": "digital",
    "monto": 23.1
  },
  {
    "id": "457838a93f97361ca8509d67bc2781f66798f284",
    "fecha": "2022-06-20",
    "comercio": "OXXO",
    "giro_comercio": "TIENDAS DE CONVENIENCIA, MINISUPER",
    "tipo_venta": "fisica",
    "monto": 14.37
  },
  {
    "id": "457838a93f97361ca8509d67bc2781f66798f284",
    "fecha": "2022-06-21",
    "comercio": "AMAZON",
    "giro_comercio": "COMERCIOS ELECTRONICOS (VTAS POR INTERNET)",
    "tipo_venta": "digital",
    "monto": 57.45
  },
  {
    "id": "457838a93f97361ca8509d67bc2781f66798f284",
    "fecha": "2022-06-21",
    "comercio": "AMAZON",
    "giro_comercio": "COMERCIOS ELECTRONICOS (VTAS POR INTERNET)",
    "tipo_venta": "digital",
    "monto": 76.66
  },
  {
    "id": "457838a93f97361ca8509d67bc2781f66798f284",
    "fecha": "2022-06-22",
    "comercio": "ATT",
    "giro_comercio": "SERVICIOS DE TELECOMUNICACION, LLAMADAS LOC Y LARG",
    "tipo_venta": "fisica",
    "monto": 65.32
  },
  {
    "id": "457838a93f97361ca8509d67bc2781f66798f284",
    "fecha": "2022-06-22",
    "comercio": "HEB",
    "giro_comercio": "AUTOSERVICIOS Y SUPERMERCADOS",
    "tipo_venta": "fisica",
    "monto": 70.66
  },
  {
    "id": "457838a93f97361ca8509d67bc2781f66798f284",
    "fecha": "2022-06-22",
    "comercio": "AMAZON",
    "giro_comercio": "COMERCIOS ELECTRONICOS (VTAS POR INTERNET)",
    "tipo_venta": "digital",
    "monto": 2.54
  },
  {
    "id": "457838a93f97361ca8509d67bc2781f66798f284",
    "fecha": "2022-06-22",
    "comercio": "AMAZON",
    "giro_comercio": "COMERCIOS ELECTRONICOS (VTAS POR INTERNET)",
    "tipo_venta": "digital",
    "monto": 90.65
  },
  {
    "id": "457838a93f97361ca8509d67bc2781f66798f284",
    "fecha": "2022-06-23",
    "comercio": "APPLE",
    "giro_comercio": NaN,
    "tipo_venta": "fisica",
    "monto": 5.87
  },
  {
    "id": "457838a93f97361ca8509d67bc2781f66798f284",
    "fecha": "2022-06-23",
    "comercio": "UBER EATS",
    "giro_comercio": "TRASLADOS - FLETES, (SERVICIOS DE MENSAJERIA)",
    "tipo_venta": "digital",
    "monto": 26.58
  },
  {
    "id": "457838a93f97361ca8509d67bc2781f66798f284",
    "fecha": "2022-06-24",
    "comercio": "APPLE",
    "giro_comercio": NaN,
    "tipo_venta": "fisica",
    "monto": 5.87
  },
  {
    "id": "457838a93f97361ca8509d67bc2781f66798f284",
    "fecha": "2022-06-25",
    "comercio": "APPLE",
    "giro_comercio": NaN,
    "tipo_venta": "fisica",
    "monto": 5.87
  },
  {
    "id": "457838a93f97361ca8509d67bc2781f66798f284",
    "fecha": "2022-06-26",
    "comercio": "APPLE",
    "giro_comercio": NaN,
    "tipo_venta": "fisica",
    "monto": 5.87
  },
  {
    "id": "457838a93f97361ca8509d67bc2781f66798f284",
    "fecha": "2022-06-27",
    "comercio": "APPLE",
    "giro_comercio": NaN,
    "tipo_venta": "fisica",
    "monto": 5.87
  },
  {
    "id": "457838a93f97361ca8509d67bc2781f66798f284",
    "fecha": "2022-06-27",
    "comercio": "DIDI FOOD",
    "giro_comercio": "COMIDA RAPIDA",
    "tipo_venta": "digital",
    "monto": 38.06
  },
  {
    "id": "457838a93f97361ca8509d67bc2781f66798f284",
    "fecha": "2022-06-28",
    "comercio": "APPLE",
    "giro_comercio": NaN,
    "tipo_venta": "fisica",
    "monto": 5.87
  },
  {
    "id": "457838a93f97361ca8509d67bc2781f66798f284",
    "fecha": "2022-06-28",
    "comercio": "OXXO",
    "giro_comercio": "TIENDAS DE CONVENIENCIA, MINISUPER",
    "tipo_venta": "fisica",
    "monto": 29.65
  },
  {
    "id": "457838a93f97361ca8509d67bc2781f66798f284",
    "fecha": "2022-06-30",
    "comercio": "UBER EATS",
    "giro_comercio": "TRASLADOS - FLETES, (SERVICIOS DE MENSAJERIA)",
    "tipo_venta": "digital",
    "monto": 26.58
  },
  {
    "id": "457838a93f97361ca8509d67bc2781f66798f284",
    "fecha": "2022-07-01",
    "comercio": "APPLE",
    "giro_comercio": NaN,
    "tipo_venta": "fisica",
    "monto": 5.87
  },
  {
    "id": "457838a93f97361ca8509d67bc2781f66798f284",
    "fecha": "2022-07-03",
    "comercio": "APPLE",
    "giro_comercio": NaN,
    "tipo_venta": "fisica",
    "monto": 5.87
  },
  {
    "id": "457838a93f97361ca8509d67bc2781f66798f284",
    "fecha": "2022-07-03",
    "comercio": "OXXO",
    "giro_comercio": "TIENDAS DE CONVENIENCIA, MINISUPER",
    "tipo_venta": "fisica",
    "monto": 9.78
  },
  {
    "id": "457838a93f97361ca8509d67bc2781f66798f284",
    "fecha": "2022-07-05",
    "comercio": "APPLE",
    "giro_comercio": NaN,
    "tipo_venta": "fisica",
    "monto": 5.87
  },
  {
    "id": "457838a93f97361ca8509d67bc2781f66798f284",
    "fecha": "2022-07-05",
    "comercio": "STARBUCKS",
    "giro_comercio": "COMIDA RAPIDA",
    "tipo_venta": "fisica",
    "monto": 21.84
  },
  {
    "id": "457838a93f97361ca8509d67bc2781f66798f284",
    "fecha": "2022-07-06",
    "comercio": "AMAZON",
    "giro_comercio": "COMERCIOS ELECTRONICOS (VTAS POR INTERNET)",
    "tipo_venta": "digital",
    "monto": 96.05
  },
  {
    "id": "457838a93f97361ca8509d67bc2781f66798f284",
    "fecha": "2022-07-06",
    "comercio": "AMAZON",
    "giro_comercio": "COMERCIOS ELECTRONICOS (VTAS POR INTERNET)",
    "tipo_venta": "digital",
    "monto": 19.09
  },
  {
    "id": "457838a93f97361ca8509d67bc2781f66798f284",
    "fecha": "2022-07-06",
    "comercio": "DIDI FOOD",
    "giro_comercio": "COMIDA RAPIDA",
    "tipo_venta": "digital",
    "monto": 43.92
  },
  {
    "id": "457838a93f97361ca8509d67bc2781f66798f284",
    "fecha": "2022-07-06",
    "comercio": "AMAZON",
    "giro_comercio": "COMERCIOS ELECTRONICOS (VTAS POR INTERNET)",
    "tipo_venta": "digital",
    "monto": 40.09
  },
  {
    "id": "457838a93f97361ca8509d67bc2781f66798f284",
    "fecha": "2022-07-08",
    "comercio": "APPLE",
    "giro_comercio": NaN,
    "tipo_venta": "fisica",
    "monto": 5.87
  },
  {
    "id": "457838a93f97361ca8509d67bc2781f66798f284",
    "fecha": "2022-07-10",
    "comercio": "APPLE",
    "giro_comercio": NaN,
    "tipo_venta": "fisica",
    "monto": 5.87
  },
  {
    "id": "457838a93f97361ca8509d67bc2781f66798f284",
    "fecha": "2022-07-11",
    "comercio": "AMAZON PRIME",
    "giro_comercio": "PAGO DE SERVICIO POR TELEVISION CABLE/POR EVENTO",
    "tipo_venta": "digital",
    "monto": 11.62
  },
  {
    "id": "457838a93f97361ca8509d67bc2781f66798f284",
    "fecha": "2022-07-11",
    "comercio": "MERCADO PAGO",
    "giro_comercio": "MERCADEO DIRECTO - NO CLASIFICADO",
    "tipo_venta": "digital",
    "monto": 91.92
  },
  {
    "id": "457838a93f97361ca8509d67bc2781f66798f284",
    "fecha": "2022-07-11",
    "comercio": "AMAZON PRIME",
    "giro_comercio": "PAGO DE SERVICIO POR TELEVISION CABLE/POR EVENTO",
    "tipo_venta": "digital",
    "monto": 11.62
  },
  {
    "id": "457838a93f97361ca8509d67bc2781f66798f284",
    "fecha": "2022-07-11",
    "comercio": "OXXO",
    "giro_comercio": "TIENDAS DE CONVENIENCIA, MINISUPER",
    "tipo_venta": "fisica",
    "monto": 28.04
  },
  {
    "id": "457838a93f97361ca8509d67bc2781f66798f284",
    "fecha": "2022-07-12",
    "comercio": "APPLE",
    "giro_comercio": NaN,
    "tipo_venta": "fisica",
    "monto": 5.87
  },
  {
    "id": "457838a93f97361ca8509d67bc2781f66798f284",
    "fecha": "2022-07-13",
    "comercio": "AMAZON",
    "giro_comercio": "COMERCIOS ELECTRONICOS (VTAS POR INTERNET)",
    "tipo_venta": "digital",
    "monto": 53.43
  },
  {
    "id": "457838a93f97361ca8509d67bc2781f66798f284",
    "fecha": "2022-07-13",
    "comercio": "UBER EATS",
    "giro_comercio": "TRASLADOS - FLETES, (SERVICIOS DE MENSAJERIA)",
    "tipo_venta": "digital",
    "monto": 39.07
  },
  {
    "id": "457838a93f97361ca8509d67bc2781f66798f284",
    "fecha": "2022-07-13",
    "comercio": "UBER",
    "giro_comercio": "LIMOSINAS, (TAXIS)",
    "tipo_venta": "digital",
    "monto": 1.6
  },
  {
    "id": "457838a93f97361ca8509d67bc2781f66798f284",
    "fecha": "2022-07-14",
    "comercio": "UBER EATS",
    "giro_comercio": "AGREGADOR",
    "tipo_venta": "digital",
    "monto": 57.34
  },
  {
    "id": "457838a93f97361ca8509d67bc2781f66798f284",
    "fecha": "2022-07-15",
    "comercio": "APPLE",
    "giro_comercio": NaN,
    "tipo_venta": "fisica",
    "monto": 5.87
  },
  {
    "id": "457838a93f97361ca8509d67bc2781f66798f284",
    "fecha": "2022-07-15",
    "comercio": "HEB",
    "giro_comercio": "AUTOSERVICIOS Y SUPERMERCADOS",
    "tipo_venta": "fisica",
    "monto": 113.92
  },
  {
    "id": "457838a93f97361ca8509d67bc2781f66798f284",
    "fecha": "2022-07-16",
    "comercio": "APPLE",
    "giro_comercio": NaN,
    "tipo_venta": "fisica",
    "monto": 69.06
  },
  {
    "id": "457838a93f97361ca8509d67bc2781f66798f284",
    "fecha": "2022-07-16",
    "comercio": "APPLE",
    "giro_comercio": NaN,
    "tipo_venta": "fisica",
    "monto": 5.87
  },
  {
    "id": "457838a93f97361ca8509d67bc2781f66798f284",
    "fecha": "2022-07-16",
    "comercio": "OXXO",
    "giro_comercio": "TIENDAS DE CONVENIENCIA, MINISUPER",
    "tipo_venta": "fisica",
    "monto": 23.96
  },
  {
    "id": "457838a93f97361ca8509d67bc2781f66798f284",
    "fecha": "2022-07-19",
    "comercio": "SPOTIFY",
    "giro_comercio": "AGREGADOR",
    "tipo_venta": "digital",
    "monto": 23.1
  },
  {
    "id": "457838a93f97361ca8509d67bc2781f66798f284",
    "fecha": "2022-07-23",
    "comercio": "APPLE",
    "giro_comercio": NaN,
    "tipo_venta": "fisica",
    "monto": 5.87
  },
  {
    "id": "457838a93f97361ca8509d67bc2781f66798f284",
    "fecha": "2022-07-24",
    "comercio": "OXXO",
    "giro_comercio": "TIENDAS DE CONVENIENCIA, MINISUPER",
    "tipo_venta": "fisica",
    "monto": 10.06
  },
  {
    "id": "457838a93f97361ca8509d67bc2781f66798f284",
    "fecha": "2022-07-25",
    "comercio": "UBER EATS",
    "giro_comercio": "TRASLADOS - FLETES, (SERVICIOS DE MENSAJERIA)",
    "tipo_venta": "digital",
    "monto": 23.79
  },
  {
    "id": "457838a93f97361ca8509d67bc2781f66798f284",
    "fecha": "2022-07-25",
    "comercio": "DIDI FOOD",
    "giro_comercio": "COMIDA RAPIDA",
    "tipo_venta": "digital",
    "monto": 27.16
  },
  {
    "id": "457838a93f97361ca8509d67bc2781f66798f284",
    "fecha": "2022-07-27",
    "comercio": "AMAZON",
    "giro_comercio": "COMERCIOS ELECTRONICOS (VTAS POR INTERNET)",
    "tipo_venta": "digital",
    "monto": 2.54
  },
  {
    "id": "457838a93f97361ca8509d67bc2781f66798f284",
    "fecha": "2022-07-27",
    "comercio": "AMAZON",
    "giro_comercio": "COMERCIOS ELECTRONICOS (VTAS POR INTERNET)",
    "tipo_venta": "digital",
    "monto": 73.65
  },
  {
    "id": "457838a93f97361ca8509d67bc2781f66798f284",
    "fecha": "2022-07-27",
    "comercio": "AMAZON",
    "giro_comercio": "COMERCIOS ELECTRONICOS (VTAS POR INTERNET)",
    "tipo_venta": "digital",
    "monto": 17.93
  },
  {
    "id": "457838a93f97361ca8509d67bc2781f66798f284",
    "fecha": "2022-07-27",
    "comercio": "UBER EATS",
    "giro_comercio": "TRASLADOS - FLETES, (SERVICIOS DE MENSAJERIA)",
    "tipo_venta": "digital",
    "monto": 23.24
  },
  {
    "id": "457838a93f97361ca8509d67bc2781f66798f284",
    "fecha": "2022-07-27",
    "comercio": "FARMACIAS GUADALAJARA",
    "giro_comercio": "DROGUERIAS, (FARMACIAS)",
    "tipo_venta": "fisica",
    "monto": 29.48
  },
  {
    "id": "457838a93f97361ca8509d67bc2781f66798f284",
    "fecha": "2022-07-27",
    "comercio": "UBER EATS",
    "giro_comercio": "TRASLADOS - FLETES, (SERVICIOS DE MENSAJERIA)",
    "tipo_venta": "digital",
    "monto": 1.53
  },
  {
    "id": "457838a93f97361ca8509d67bc2781f66798f284",
    "fecha": "2022-07-28",
    "comercio": "UBER EATS",
    "giro_comercio": "TRASLADOS - FLETES, (SERVICIOS DE MENSAJERIA)",
    "tipo_venta": "digital",
    "monto": 29.32
  },
  {
    "id": "457838a93f97361ca8509d67bc2781f66798f284",
    "fecha": "2022-08-02",
    "comercio": "OXXO",
    "giro_comercio": "TIENDAS DE CONVENIENCIA, MINISUPER",
    "tipo_venta": "fisica",
    "monto": 12.53
  },
  {
    "id": "457838a93f97361ca8509d67bc2781f66798f284",
    "fecha": "2022-08-03",
    "comercio": "STARBUCKS",
    "giro_comercio": "COMIDA RAPIDA",
    "tipo_venta": "fisica",
    "monto": 15.06
  },
  {
    "id": "457838a93f97361ca8509d67bc2781f66798f284",
    "fecha": "2022-08-04",
    "comercio": "MERCADO PAGO",
    "giro_comercio": "MERCADEO DIRECTO - NO CLASIFICADO",
    "tipo_venta": "digital",
    "monto": 331.83
  },
  {
    "id": "457838a93f97361ca8509d67bc2781f66798f284",
    "fecha": "2022-08-10",
    "comercio": "UBER",
    "giro_comercio": "AGREGADOR",
    "tipo_venta": "digital",
    "monto": 8.28
  },
  {
    "id": "457838a93f97361ca8509d67bc2781f66798f284",
    "fecha": "2022-08-16",
    "comercio": "APPLE",
    "giro_comercio": NaN,
    "tipo_venta": "fisica",
    "monto": 69.06
  },
  {
    "id": "457838a93f97361ca8509d67bc2781f66798f284",
    "fecha": "2022-08-19",
    "comercio": "SPOTIFY",
    "giro_comercio": "AGREGADOR",
    "tipo_venta": "digital",
    "monto": 23.1
  },
  {
    "id": "457838a93f97361ca8509d67bc2781f66798f284",
    "fecha": "2022-08-23",
    "comercio": "STARBUCKS",
    "giro_comercio": "COMIDA RAPIDA",
    "tipo_venta": "fisica",
    "monto": 16.31
  },
  {
    "id": "457838a93f97361ca8509d67bc2781f66798f284",
    "fecha": "2022-08-23",
    "comercio": "APPLE",
    "giro_comercio": NaN,
    "tipo_venta": "fisica",
    "monto": 5.87
  },
  {
    "id": "457838a93f97361ca8509d67bc2781f66798f284",
    "fecha": "2022-08-25",
    "comercio": "UBER EATS",
    "giro_comercio": "AGREGADOR",
    "tipo_venta": "digital",
    "monto": 44.24
  },
  {
    "id": "457838a93f97361ca8509d67bc2781f66798f284",
    "fecha": "2022-08-28",
    "comercio": "OXXO",
    "giro_comercio": "TIENDAS DE CONVENIENCIA, MINISUPER",
    "tipo_venta": "fisica",
    "monto": 20.81
  },
  {
    "id": "457838a93f97361ca8509d67bc2781f66798f284",
    "fecha": "2022-08-29",
    "comercio": "UBER EATS",
    "giro_comercio": "TRASLADOS - FLETES, (SERVICIOS DE MENSAJERIA)",
    "tipo_venta": "digital",
    "monto": 19.09
  },
  {
    "id": "457838a93f97361ca8509d67bc2781f66798f284",
    "fecha": "2022-08-30",
    "comercio": "UBER EATS",
    "giro_comercio": "TRASLADOS - FLETES, (SERVICIOS DE MENSAJERIA)",
    "tipo_venta": "digital",
    "monto": 20.35
  },
  {
    "id": "457838a93f97361ca8509d67bc2781f66798f284",
    "fecha": "2022-08-31",
    "comercio": "UBER EATS",
    "giro_comercio": "AGREGADOR",
    "tipo_venta": "digital",
    "monto": 20.81
  },
  {
    "id": "457838a93f97361ca8509d67bc2781f66798f284",
    "fecha": "2022-09-01",
    "comercio": "DIDIFOOD",
    "giro_comercio": "COMIDA RAPIDA",
    "tipo_venta": "digital",
    "monto": 29.83
  },
  {
    "id": "457838a93f97361ca8509d67bc2781f66798f284",
    "fecha": "2022-09-04",
    "comercio": "MERCADO PAGO",
    "giro_comercio": "MERCADEO DIRECTO - NO CLASIFICADO",
    "tipo_venta": "digital",
    "monto": 816.79
  },
  {
    "id": "457838a93f97361ca8509d67bc2781f66798f284",
    "fecha": "2022-09-05",
    "comercio": "OXXO",
    "giro_comercio": "TIENDAS DE CONVENIENCIA, MINISUPER",
    "tipo_venta": "fisica",
    "monto": 14.83
  },
  {
    "id": "457838a93f97361ca8509d67bc2781f66798f284",
    "fecha": "2022-09-06",
    "comercio": "UBER EATS",
    "giro_comercio": "AGREGADOR",
    "tipo_venta": "digital",
    "monto": 19.08
  },
  {
    "id": "457838a93f97361ca8509d67bc2781f66798f284",
    "fecha": "2022-09-06",
    "comercio": "OXXO",
    "giro_comercio": "TIENDAS DE CONVENIENCIA, MINISUPER",
    "tipo_venta": "fisica",
    "monto": 48.61
  },
  {
    "id": "457838a93f97361ca8509d67bc2781f66798f284",
    "fecha": "2022-09-08",
    "comercio": "UBER EATS",
    "giro_comercio": "TRASLADOS - FLETES, (SERVICIOS DE MENSAJERIA)",
    "tipo_venta": "digital",
    "monto": 23.1
  },
  {
    "id": "457838a93f97361ca8509d67bc2781f66798f284",
    "fecha": "2022-09-09",
    "comercio": "UBER",
    "giro_comercio": "AGREGADOR",
    "tipo_venta": "digital",
    "monto": 8.28
  },
  {
    "id": "457838a93f97361ca8509d67bc2781f66798f284",
    "fecha": "2022-09-11",
    "comercio": "AMAZON PRIME",
    "giro_comercio": "PAGO DE SERVICIO POR TELEVISION CABLE/POR EVENTO",
    "tipo_venta": "digital",
    "monto": 11.62
  },
  {
    "id": "457838a93f97361ca8509d67bc2781f66798f284",
    "fecha": "2022-09-12",
    "comercio": "UBER EATS",
    "giro_comercio": "TRASLADOS - FLETES, (SERVICIOS DE MENSAJERIA)",
    "tipo_venta": "digital",
    "monto": 18.73
  },
  {
    "id": "457838a93f97361ca8509d67bc2781f66798f284",
    "fecha": "2022-09-14",
    "comercio": "UBER EATS",
    "giro_comercio": "AGREGADOR",
    "tipo_venta": "digital",
    "monto": 20.83
  },
  {
    "id": "457838a93f97361ca8509d67bc2781f66798f284",
    "fecha": "2022-09-15",
    "comercio": "UBER EATS",
    "giro_comercio": "TRASLADOS - FLETES, (SERVICIOS DE MENSAJERIA)",
    "tipo_venta": "digital",
    "monto": 24.25
  },
  {
    "id": "457838a93f97361ca8509d67bc2781f66798f284",
    "fecha": "2022-09-18",
    "comercio": "OXXO",
    "giro_comercio": "TIENDAS DE CONVENIENCIA, MINISUPER",
    "tipo_venta": "fisica",
    "monto": 17.93
  },
  {
    "id": "457838a93f97361ca8509d67bc2781f66798f284",
    "fecha": "2022-09-19",
    "comercio": "SPOTIFY",
    "giro_comercio": "AGREGADOR",
    "tipo_venta": "digital",
    "monto": 23.1
  },
  {
    "id": "457838a93f97361ca8509d67bc2781f66798f284",
    "fecha": "2022-09-21",
    "comercio": "UBER EATS",
    "giro_comercio": "TRASLADOS - FLETES, (SERVICIOS DE MENSAJERIA)",
    "tipo_venta": "digital",
    "monto": 35.63
  },
  {
    "id": "457838a93f97361ca8509d67bc2781f66798f284",
    "fecha": "2022-09-22",
    "comercio": "UBER EATS",
    "giro_comercio": "AGREGADOR",
    "tipo_venta": "digital",
    "monto": 23.1
  },
  {
    "id": "457838a93f97361ca8509d67bc2781f66798f284",
    "fecha": "2022-09-23",
    "comercio": "APPLE",
    "giro_comercio": NaN,
    "tipo_venta": "fisica",
    "monto": 5.87
  },
  {
    "id": "457838a93f97361ca8509d67bc2781f66798f284",
    "fecha": "2022-09-26",
    "comercio": "AMAZON",
    "giro_comercio": "COMERCIOS ELECTRONICOS (VTAS POR INTERNET)",
    "tipo_venta": "digital",
    "monto": 2.54
  },
  {
    "id": "457838a93f97361ca8509d67bc2781f66798f284",
    "fecha": "2022-09-26",
    "comercio": "AMAZON",
    "giro_comercio": "COMERCIOS ELECTRONICOS (VTAS POR INTERNET)",
    "tipo_venta": "digital",
    "monto": 72.04
  },
  {
    "id": "457838a93f97361ca8509d67bc2781f66798f284",
    "fecha": "2022-09-26",
    "comercio": "OXXO",
    "giro_comercio": "TIENDAS DE CONVENIENCIA, MINISUPER",
    "tipo_venta": "fisica",
    "monto": 17.01
  },
  {
    "id": "457838a93f97361ca8509d67bc2781f66798f284",
    "fecha": "2022-09-27",
    "comercio": "UBER EATS",
    "giro_comercio": "TRASLADOS - FLETES, (SERVICIOS DE MENSAJERIA)",
    "tipo_venta": "digital",
    "monto": 13.63
  },
  {
    "id": "457838a93f97361ca8509d67bc2781f66798f284",
    "fecha": "2022-09-27",
    "comercio": "UBER EATS",
    "giro_comercio": "AGREGADOR",
    "tipo_venta": "digital",
    "monto": 27.01
  },
  {
    "id": "457838a93f97361ca8509d67bc2781f66798f284",
    "fecha": "2022-09-27",
    "comercio": "OXXO",
    "giro_comercio": "TIENDAS DE CONVENIENCIA, MINISUPER",
    "tipo_venta": "fisica",
    "monto": 18.97
  },
  {
    "id": "457838a93f97361ca8509d67bc2781f66798f284",
    "fecha": "2022-09-27",
    "comercio": "OXXO",
    "giro_comercio": "TIENDAS DE CONVENIENCIA, MINISUPER",
    "tipo_venta": "fisica",
    "monto": 5.41
  },
  {
    "id": "457838a93f97361ca8509d67bc2781f66798f284",
    "fecha": "2022-10-04",
    "comercio": "UBER EATS",
    "giro_comercio": "TRASLADOS - FLETES, (SERVICIOS DE MENSAJERIA)",
    "tipo_venta": "digital",
    "monto": 13.63
  },
  {
    "id": "457838a93f97361ca8509d67bc2781f66798f284",
    "fecha": "2022-10-04",
    "comercio": "MERCADO PAGO",
    "giro_comercio": "MERCADEO DIRECTO - NO CLASIFICADO",
    "tipo_venta": "digital",
    "monto": 816.79
  },
  {
    "id": "457838a93f97361ca8509d67bc2781f66798f284",
    "fecha": "2022-10-06",
    "comercio": "UBER EATS",
    "giro_comercio": "AGREGADOR",
    "tipo_venta": "digital",
    "monto": 36.31
  },
  {
    "id": "457838a93f97361ca8509d67bc2781f66798f284",
    "fecha": "2022-10-08",
    "comercio": "FARMACIAS GUADALAJARA",
    "giro_comercio": "DROGUERIAS, (FARMACIAS)",
    "tipo_venta": "fisica",
    "monto": 18.28
  },
  {
    "id": "457838a93f97361ca8509d67bc2781f66798f284",
    "fecha": "2022-10-09",
    "comercio": "UBER",
    "giro_comercio": "AGREGADOR",
    "tipo_venta": "digital",
    "monto": 8.28
  },
  {
    "id": "457838a93f97361ca8509d67bc2781f66798f284",
    "fecha": "2022-10-11",
    "comercio": "AMAZON PRIME",
    "giro_comercio": "PAGO DE SERVICIO POR TELEVISION CABLE/POR EVENTO",
    "tipo_venta": "digital",
    "monto": 11.62
  },
  {
    "id": "457838a93f97361ca8509d67bc2781f66798f284",
    "fecha": "2022-10-11",
    "comercio": "UBER EATS",
    "giro_comercio": "TRASLADOS - FLETES, (SERVICIOS DE MENSAJERIA)",
    "tipo_venta": "digital",
    "monto": 22.0
  },
  {
    "id": "457838a93f97361ca8509d67bc2781f66798f284",
    "fecha": "2022-10-13",
    "comercio": "UBER EATS",
    "giro_comercio": "AGREGADOR",
    "tipo_venta": "digital",
    "monto": 16.89
  },
  {
    "id": "457838a93f97361ca8509d67bc2781f66798f284",
    "fecha": "2022-10-15",
    "comercio": "AMAZON",
    "giro_comercio": "COMERCIOS ELECTRONICOS (VTAS POR INTERNET)",
    "tipo_venta": "digital",
    "monto": 49.07
  },
  {
    "id": "457838a93f97361ca8509d67bc2781f66798f284",
    "fecha": "2022-10-15",
    "comercio": "MERCADO PAGO",
    "giro_comercio": "MERCADEO DIRECTO - NO CLASIFICADO",
    "tipo_venta": "digital",
    "monto": 24.83
  },
  {
    "id": "457838a93f97361ca8509d67bc2781f66798f284",
    "fecha": "2022-10-17",
    "comercio": "UBER EATS",
    "giro_comercio": "AGREGADOR",
    "tipo_venta": "digital",
    "monto": 19.77
  },
  {
    "id": "457838a93f97361ca8509d67bc2781f66798f284",
    "fecha": "2022-10-17",
    "comercio": "KUESKI PAY",
    "giro_comercio": "ASESOR FINANCIERO,CONSEJEROS, MATRIMONIAL,PRESTAMO",
    "tipo_venta": "digital",
    "monto": 71.93
  },
  {
    "id": "457838a93f97361ca8509d67bc2781f66798f284",
    "fecha": "2022-10-18",
    "comercio": "UBER EATS",
    "giro_comercio": "TRASLADOS - FLETES, (SERVICIOS DE MENSAJERIA)",
    "tipo_venta": "digital",
    "monto": 39.3
  },
  {
    "id": "457838a93f97361ca8509d67bc2781f66798f284",
    "fecha": "2022-10-18",
    "comercio": "HEB",
    "giro_comercio": "AUTOSERVICIOS Y SUPERMERCADOS",
    "tipo_venta": "fisica",
    "monto": 71.99
  },
  {
    "id": "457838a93f97361ca8509d67bc2781f66798f284",
    "fecha": "2022-10-19",
    "comercio": "SPOTIFY",
    "giro_comercio": "AGREGADOR",
    "tipo_venta": "digital",
    "monto": 23.1
  },
  {
    "id": "457838a93f97361ca8509d67bc2781f66798f284",
    "fecha": "2022-10-20",
    "comercio": "UBER EATS",
    "giro_comercio": "TRASLADOS - FLETES, (SERVICIOS DE MENSAJERIA)",
    "tipo_venta": "digital",
    "monto": 24.25
  },
  {
    "id": "457838a93f97361ca8509d67bc2781f66798f284",
    "fecha": "2022-10-23",
    "comercio": "APPLE",
    "giro_comercio": NaN,
    "tipo_venta": "fisica",
    "monto": 5.87
  },
  {
    "id": "457838a93f97361ca8509d67bc2781f66798f284",
    "fecha": "2022-10-23",
    "comercio": "UBER EATS",
    "giro_comercio": "AGREGADOR",
    "tipo_venta": "digital",
    "monto": 23.25
  },
  {
    "id": "457838a93f97361ca8509d67bc2781f66798f284",
    "fecha": "2022-10-24",
    "comercio": "UBER EATS",
    "giro_comercio": "TRASLADOS - FLETES, (SERVICIOS DE MENSAJERIA)",
    "tipo_venta": "digital",
    "monto": 19.79
  },
  {
    "id": "457838a93f97361ca8509d67bc2781f66798f284",
    "fecha": "2022-10-24",
    "comercio": "UBER EATS",
    "giro_comercio": "TRASLADOS - FLETES, (SERVICIOS DE MENSAJERIA)",
    "tipo_venta": "digital",
    "monto": 27.7
  },
  {
    "id": "457838a93f97361ca8509d67bc2781f66798f284",
    "fecha": "2022-10-25",
    "comercio": "UBER EATS",
    "giro_comercio": "TRASLADOS - FLETES, (SERVICIOS DE MENSAJERIA)",
    "tipo_venta": "digital",
    "monto": 46.19
  },
  {
    "id": "457838a93f97361ca8509d67bc2781f66798f284",
    "fecha": "2022-10-30",
    "comercio": "KUESKI PAY",
    "giro_comercio": "ASESOR FINANCIERO,CONSEJEROS, MATRIMONIAL,PRESTAMO",
    "tipo_venta": "digital",
    "monto": 65.26
  },
  {
    "id": "457838a93f97361ca8509d67bc2781f66798f284",
    "fecha": "2022-10-31",
    "comercio": "UBER EATS",
    "giro_comercio": "TRASLADOS - FLETES, (SERVICIOS DE MENSAJERIA)",
    "tipo_venta": "digital",
    "monto": 24.25
  },
  {
    "id": "457838a93f97361ca8509d67bc2781f66798f284",
    "fecha": "2022-11-01",
    "comercio": "UBER EATS",
    "giro_comercio": "TRASLADOS - FLETES, (SERVICIOS DE MENSAJERIA)",
    "tipo_venta": "digital",
    "monto": 30.34
  },
  {
    "id": "457838a93f97361ca8509d67bc2781f66798f284",
    "fecha": "2022-11-01",
    "comercio": "OXXO",
    "giro_comercio": "TIENDAS DE CONVENIENCIA, MINISUPER",
    "tipo_venta": "fisica",
    "monto": 13.45
  },
  {
    "id": "457838a93f97361ca8509d67bc2781f66798f284",
    "fecha": "2022-11-03",
    "comercio": "NETFLIX",
    "giro_comercio": "MERCADEO DIRECTO - NO CLASIFICADO",
    "tipo_venta": "digital",
    "monto": 34.59
  },
  {
    "id": "457838a93f97361ca8509d67bc2781f66798f284",
    "fecha": "2022-11-03",
    "comercio": "MERCADO PAGO",
    "giro_comercio": "COMERCIOS ELECTRONICOS (VTAS POR INTERNET)",
    "tipo_venta": "digital",
    "monto": 816.79
  },
  {
    "id": "457838a93f97361ca8509d67bc2781f66798f284",
    "fecha": "2022-11-04",
    "comercio": "FARMACIAS GUADALAJARA",
    "giro_comercio": "DROGUERIAS, (FARMACIAS)",
    "tipo_venta": "fisica",
    "monto": 25.43
  },
  {
    "id": "457838a93f97361ca8509d67bc2781f66798f284",
    "fecha": "2022-11-05",
    "comercio": "AMAZON",
    "giro_comercio": "COMERCIOS ELECTRONICOS (VTAS POR INTERNET)",
    "tipo_venta": "digital",
    "monto": 25.75
  },
  {
    "id": "457838a93f97361ca8509d67bc2781f66798f284",
    "fecha": "2022-11-08",
    "comercio": "UBER EATS",
    "giro_comercio": "TRASLADOS - FLETES, (SERVICIOS DE MENSAJERIA)",
    "tipo_venta": "digital",
    "monto": 15.86
  },
  {
    "id": "457838a93f97361ca8509d67bc2781f66798f284",
    "fecha": "2022-11-08",
    "comercio": "UBER EATS",
    "giro_comercio": "TRASLADOS - FLETES, (SERVICIOS DE MENSAJERIA)",
    "tipo_venta": "digital",
    "monto": 29.54
  },
  {
    "id": "457838a93f97361ca8509d67bc2781f66798f284",
    "fecha": "2022-11-09",
    "comercio": "UBER",
    "giro_comercio": "AGREGADOR",
    "tipo_venta": "digital",
    "monto": 8.28
  },
  {
    "id": "457838a93f97361ca8509d67bc2781f66798f284",
    "fecha": "2022-11-10",
    "comercio": "UBER EATS",
    "giro_comercio": "TRASLADOS - FLETES, (SERVICIOS DE MENSAJERIA)",
    "tipo_venta": "digital",
    "monto": 28.27
  },
  {
    "id": "457838a93f97361ca8509d67bc2781f66798f284",
    "fecha": "2022-11-11",
    "comercio": "AMAZON PRIME",
    "giro_comercio": "PAGO DE SERVICIO POR TELEVISION CABLE/POR EVENTO",
    "tipo_venta": "digital",
    "monto": 11.62
  },
  {
    "id": "457838a93f97361ca8509d67bc2781f66798f284",
    "fecha": "2022-11-11",
    "comercio": "UBER EATS",
    "giro_comercio": "TRASLADOS - FLETES, (SERVICIOS DE MENSAJERIA)",
    "tipo_venta": "digital",
    "monto": 21.85
  },
  {
    "id": "457838a93f97361ca8509d67bc2781f66798f284",
    "fecha": "2022-11-15",
    "comercio": "KUESKI PAY",
    "giro_comercio": "ASESOR FINANCIERO,CONSEJEROS, MATRIMONIAL,PRESTAMO",
    "tipo_venta": "digital",
    "monto": 65.26
  },
  {
    "id": "457838a93f97361ca8509d67bc2781f66798f284",
    "fecha": "2022-11-19",
    "comercio": "UBER EATS",
    "giro_comercio": "AGREGADOR",
    "tipo_venta": "digital",
    "monto": 13.56
  },
  {
    "id": "457838a93f97361ca8509d67bc2781f66798f284",
    "fecha": "2022-11-19",
    "comercio": "SPOTIFY",
    "giro_comercio": "AGREGADOR",
    "tipo_venta": "digital",
    "monto": 23.1
  },
  {
    "id": "457838a93f97361ca8509d67bc2781f66798f284",
    "fecha": "2022-11-21",
    "comercio": "UBER EATS",
    "giro_comercio": "TRASLADOS - FLETES, (SERVICIOS DE MENSAJERIA)",
    "tipo_venta": "digital",
    "monto": 38.73
  },
  {
    "id": "457838a93f97361ca8509d67bc2781f66798f284",
    "fecha": "2022-11-22",
    "comercio": "UBER EATS",
    "giro_comercio": "AGREGADOR",
    "tipo_venta": "digital",
    "monto": 17.3
  },
  {
    "id": "457838a93f97361ca8509d67bc2781f66798f284",
    "fecha": "2022-11-22",
    "comercio": "UBER EATS",
    "giro_comercio": "TRASLADOS - FLETES, (SERVICIOS DE MENSAJERIA)",
    "tipo_venta": "digital",
    "monto": 31.6
  },
  {
    "id": "457838a93f97361ca8509d67bc2781f66798f284",
    "fecha": "2022-11-22",
    "comercio": "UBER EATS",
    "giro_comercio": "TRASLADOS - FLETES, (SERVICIOS DE MENSAJERIA)",
    "tipo_venta": "digital",
    "monto": 70.21
  },
  {
    "id": "457838a93f97361ca8509d67bc2781f66798f284",
    "fecha": "2022-11-23",
    "comercio": "UBER EATS",
    "giro_comercio": "TRASLADOS - FLETES, (SERVICIOS DE MENSAJERIA)",
    "tipo_venta": "digital",
    "monto": 36.89
  },
  {
    "id": "457838a93f97361ca8509d67bc2781f66798f284",
    "fecha": "2022-11-24",
    "comercio": "APPLE",
    "giro_comercio": NaN,
    "tipo_venta": "fisica",
    "monto": 5.87
  },
  {
    "id": "457838a93f97361ca8509d67bc2781f66798f284",
    "fecha": "2022-11-24",
    "comercio": "UBER EATS",
    "giro_comercio": "AGREGADOR",
    "tipo_venta": "digital",
    "monto": 52.86
  },
  {
    "id": "457838a93f97361ca8509d67bc2781f66798f284",
    "fecha": "2022-11-25",
    "comercio": "UBER EATS",
    "giro_comercio": "TRASLADOS - FLETES, (SERVICIOS DE MENSAJERIA)",
    "tipo_venta": "digital",
    "monto": 19.73
  },
  {
    "id": "457838a93f97361ca8509d67bc2781f66798f284",
    "fecha": "2022-11-26",
    "comercio": "FARMACIAS DEL AHORRO",
    "giro_comercio": "DROGUERIAS, (FARMACIAS)",
    "tipo_venta": "fisica",
    "monto": 16.9
  },
  {
    "id": "457838a93f97361ca8509d67bc2781f66798f284",
    "fecha": "2022-11-28",
    "comercio": "UBER EATS",
    "giro_comercio": "TRASLADOS - FLETES, (SERVICIOS DE MENSAJERIA)",
    "tipo_venta": "digital",
    "monto": 19.77
  },
  {
    "id": "457838a93f97361ca8509d67bc2781f66798f284",
    "fecha": "2022-11-29",
    "comercio": "NETFLIX",
    "giro_comercio": "PAGO DE SERVICIO POR TELEVISION CABLE/POR EVENTO",
    "tipo_venta": "digital",
    "monto": 34.59
  },
  {
    "id": "457838a93f97361ca8509d67bc2781f66798f284",
    "fecha": "2022-11-29",
    "comercio": "UBER EATS",
    "giro_comercio": "TRASLADOS - FLETES, (SERVICIOS DE MENSAJERIA)",
    "tipo_venta": "digital",
    "monto": 31.26
  },
  {
    "id": "457838a93f97361ca8509d67bc2781f66798f284",
    "fecha": "2022-11-29",
    "comercio": "UBER EATS",
    "giro_comercio": "AGREGADOR",
    "tipo_venta": "digital",
    "monto": 17.3
  },
  {
    "id": "457838a93f97361ca8509d67bc2781f66798f284",
    "fecha": "2022-11-30",
    "comercio": "CARLS JR",
    "giro_comercio": "COMIDA RAPIDA",
    "tipo_venta": "fisica",
    "monto": 76.87
  },
  {
    "id": "457838a93f97361ca8509d67bc2781f66798f284",
    "fecha": "2022-12-02",
    "comercio": "MERCADO PAGO",
    "giro_comercio": "COMERCIOS ELECTRONICOS (VTAS POR INTERNET)",
    "tipo_venta": "digital",
    "monto": 27.24
  },
  {
    "id": "457838a93f97361ca8509d67bc2781f66798f284",
    "fecha": "2022-12-03",
    "comercio": "MERCADOPAGO",
    "giro_comercio": "MERCADO DIRECTO - VENTAS POR CATALOGO",
    "tipo_venta": "digital",
    "monto": 331.83
  },
  {
    "id": "457838a93f97361ca8509d67bc2781f66798f284",
    "fecha": "2022-12-04",
    "comercio": "AMAZON",
    "giro_comercio": "COMERCIOS ELECTRONICOS (VTAS POR INTERNET)",
    "tipo_venta": "digital",
    "monto": 45.05
  },
  {
    "id": "457838a93f97361ca8509d67bc2781f66798f284",
    "fecha": "2022-12-04",
    "comercio": "UBER EATS",
    "giro_comercio": "AGREGADOR",
    "tipo_venta": "digital",
    "monto": 34.48
  },
  {
    "id": "457838a93f97361ca8509d67bc2781f66798f284",
    "fecha": "2022-12-05",
    "comercio": "UBER EATS",
    "giro_comercio": "AGREGADOR",
    "tipo_venta": "digital",
    "monto": 21.91
  },
  {
    "id": "457838a93f97361ca8509d67bc2781f66798f284",
    "fecha": "2022-12-06",
    "comercio": "UBER EATS",
    "giro_comercio": "AGREGADOR",
    "tipo_venta": "digital",
    "monto": 22.07
  },
  {
    "id": "457838a93f97361ca8509d67bc2781f66798f284",
    "fecha": "2022-12-08",
    "comercio": "MERCADO PAGO",
    "giro_comercio": "COMERCIOS ELECTRONICOS (VTAS POR INTERNET)",
    "tipo_venta": "digital",
    "monto": 132.79
  },
  {
    "id": "457838a93f97361ca8509d67bc2781f66798f284",
    "fecha": "2022-12-09",
    "comercio": "UBER EATS",
    "giro_comercio": "TRASLADOS - FLETES, (SERVICIOS DE MENSAJERIA)",
    "tipo_venta": "digital",
    "monto": 30.64
  },
  {
    "id": "457838a93f97361ca8509d67bc2781f66798f284",
    "fecha": "2022-12-09",
    "comercio": "UBER",
    "giro_comercio": "AGREGADOR",
    "tipo_venta": "digital",
    "monto": 8.28
  },
  {
    "id": "457838a93f97361ca8509d67bc2781f66798f284",
    "fecha": "2022-12-11",
    "comercio": "AMAZON PRIME",
    "giro_comercio": "PAGO DE SERVICIO POR TELEVISION CABLE/POR EVENTO",
    "tipo_venta": "digital",
    "monto": 11.62
  },
  {
    "id": "457838a93f97361ca8509d67bc2781f66798f284",
    "fecha": "2022-12-11",
    "comercio": "APPLE",
    "giro_comercio": NaN,
    "tipo_venta": "fisica",
    "monto": 63.31
  },
  {
    "id": "457838a93f97361ca8509d67bc2781f66798f284",
    "fecha": "2022-12-11",
    "comercio": "UBER EATS",
    "giro_comercio": "AGREGADOR",
    "tipo_venta": "digital",
    "monto": 30.62
  },
  {
    "id": "457838a93f97361ca8509d67bc2781f66798f284",
    "fecha": "2022-12-15",
    "comercio": "AMAZON",
    "giro_comercio": "COMERCIOS ELECTRONICOS (VTAS POR INTERNET)",
    "tipo_venta": "digital",
    "monto": 187.73
  },
  {
    "id": "457838a93f97361ca8509d67bc2781f66798f284",
    "fecha": "2022-12-16",
    "comercio": "UBER EATS",
    "giro_comercio": "TRASLADOS - FLETES, (SERVICIOS DE MENSAJERIA)",
    "tipo_venta": "digital",
    "monto": 22.75
  },
  {
    "id": "457838a93f97361ca8509d67bc2781f66798f284",
    "fecha": "2022-12-16",
    "comercio": "UBER EATS",
    "giro_comercio": "AGREGADOR",
    "tipo_venta": "digital",
    "monto": 1.5
  },
  {
    "id": "457838a93f97361ca8509d67bc2781f66798f284",
    "fecha": "2022-12-16",
    "comercio": "UBER EATS",
    "giro_comercio": "AGREGADOR",
    "tipo_venta": "digital",
    "monto": 1.5
  },
  {
    "id": "457838a93f97361ca8509d67bc2781f66798f284",
    "fecha": "2022-12-17",
    "comercio": "APPLE",
    "giro_comercio": NaN,
    "tipo_venta": "fisica",
    "monto": 63.31
  },
  {
    "id": "457838a93f97361ca8509d67bc2781f66798f284",
    "fecha": "2022-12-17",
    "comercio": "APPLE",
    "giro_comercio": NaN,
    "tipo_venta": "fisica",
    "monto": 28.85
  },
  {
    "id": "457838a93f97361ca8509d67bc2781f66798f284",
    "fecha": "2022-12-17",
    "comercio": "AMAZON",
    "giro_comercio": "COMERCIOS ELECTRONICOS (VTAS POR INTERNET)",
    "tipo_venta": "digital",
    "monto": 143.73
  },
  {
    "id": "457838a93f97361ca8509d67bc2781f66798f284",
    "fecha": "2022-12-19",
    "comercio": "SPOTIFY",
    "giro_comercio": "AGREGADOR",
    "tipo_venta": "digital",
    "monto": 23.1
  },
  {
    "id": "457838a93f97361ca8509d67bc2781f66798f284",
    "fecha": "2022-12-20",
    "comercio": "UBER EATS",
    "giro_comercio": "AGREGADOR",
    "tipo_venta": "digital",
    "monto": 19.77
  },
  {
    "id": "457838a93f97361ca8509d67bc2781f66798f284",
    "fecha": "2022-12-20",
    "comercio": "UBER EATS",
    "giro_comercio": "TRASLADOS - FLETES, (SERVICIOS DE MENSAJERIA)",
    "tipo_venta": "digital",
    "monto": 30.0
  },
  {
    "id": "457838a93f97361ca8509d67bc2781f66798f284",
    "fecha": "2022-12-20",
    "comercio": "OXXO",
    "giro_comercio": "TIENDAS DE CONVENIENCIA, MINISUPER",
    "tipo_venta": "fisica",
    "monto": 13.11
  },
  {
    "id": "457838a93f97361ca8509d67bc2781f66798f284",
    "fecha": "2022-12-21",
    "comercio": "UBER EATS",
    "giro_comercio": "AGREGADOR",
    "tipo_venta": "digital",
    "monto": 23.68
  },
  {
    "id": "457838a93f97361ca8509d67bc2781f66798f284",
    "fecha": "2022-12-22",
    "comercio": "UBER EATS",
    "giro_comercio": "AGREGADOR",
    "tipo_venta": "digital",
    "monto": 22.02
  },
  {
    "id": "457838a93f97361ca8509d67bc2781f66798f284",
    "fecha": "2022-12-22",
    "comercio": "MERCADO PAGO",
    "giro_comercio": "COMERCIOS ELECTRONICOS (VTAS POR INTERNET)",
    "tipo_venta": "digital",
    "monto": 34.62
  },
  {
    "id": "457838a93f97361ca8509d67bc2781f66798f284",
    "fecha": "2022-12-24",
    "comercio": "APPLE",
    "giro_comercio": NaN,
    "tipo_venta": "fisica",
    "monto": 5.87
  },
  {
    "id": "457838a93f97361ca8509d67bc2781f66798f284",
    "fecha": "2022-12-24",
    "comercio": "APPLE",
    "giro_comercio": NaN,
    "tipo_venta": "fisica",
    "monto": 5.87
  },
  {
    "id": "457838a93f97361ca8509d67bc2781f66798f284",
    "fecha": "2022-12-25",
    "comercio": "APPLE",
    "giro_comercio": NaN,
    "tipo_venta": "fisica",
    "monto": 5.87
  },
  {
    "id": "457838a93f97361ca8509d67bc2781f66798f284",
    "fecha": "2022-12-25",
    "comercio": "UBER EATS",
    "giro_comercio": "AGREGADOR",
    "tipo_venta": "digital",
    "monto": 45.27
  },
  {
    "id": "457838a93f97361ca8509d67bc2781f66798f284",
    "fecha": "2022-12-26",
    "comercio": "APPLE",
    "giro_comercio": NaN,
    "tipo_venta": "fisica",
    "monto": 5.87
  },
  {
    "id": "457838a93f97361ca8509d67bc2781f66798f284",
    "fecha": "2022-12-26",
    "comercio": "UBER EATS",
    "giro_comercio": "TRASLADOS - FLETES, (SERVICIOS DE MENSAJERIA)",
    "tipo_venta": "digital",
    "monto": 37.46
  },
  {
    "id": "457838a93f97361ca8509d67bc2781f66798f284",
    "fecha": "2022-12-27",
    "comercio": "UBER EATS",
    "giro_comercio": "TRASLADOS - FLETES, (SERVICIOS DE MENSAJERIA)",
    "tipo_venta": "digital",
    "monto": 20.35
  },
  {
    "id": "457838a93f97361ca8509d67bc2781f66798f284",
    "fecha": "2022-12-27",
    "comercio": "UBER EATS",
    "giro_comercio": "AGREGADOR",
    "tipo_venta": "digital",
    "monto": 20.35
  },
  {
    "id": "457838a93f97361ca8509d67bc2781f66798f284",
    "fecha": "2022-12-28",
    "comercio": "APPLE",
    "giro_comercio": NaN,
    "tipo_venta": "fisica",
    "monto": 5.87
  },
  {
    "id": "457838a93f97361ca8509d67bc2781f66798f284",
    "fecha": "2022-12-28",
    "comercio": "UBER EATS",
    "giro_comercio": "TRASLADOS - FLETES, (SERVICIOS DE MENSAJERIA)",
    "tipo_venta": "digital",
    "monto": 26.89
  },
  {
    "id": "457838a93f97361ca8509d67bc2781f66798f284",
    "fecha": "2022-12-29",
    "comercio": "NETFLIX",
    "giro_comercio": "PAGO DE SERVICIO POR TELEVISION CABLE/POR EVENTO",
    "tipo_venta": "digital",
    "monto": 38.04
  },
  {
    "id": "457838a93f97361ca8509d67bc2781f66798f284",
    "fecha": "2022-12-29",
    "comercio": "NETFLIX",
    "giro_comercio": "PAGO DE SERVICIO POR TELEVISION CABLE/POR EVENTO",
    "tipo_venta": "digital",
    "monto": 38.04
  },
  {
    "id": "457838a93f97361ca8509d67bc2781f66798f284",
    "fecha": "2022-12-29",
    "comercio": "UBER EATS",
    "giro_comercio": "TRASLADOS - FLETES, (SERVICIOS DE MENSAJERIA)",
    "tipo_venta": "digital",
    "monto": 25.65
  },
  {
    "id": "457838a93f97361ca8509d67bc2781f66798f284",
    "fecha": "2022-12-29",
    "comercio": "UBER EATS",
    "giro_comercio": "TRASLADOS - FLETES, (SERVICIOS DE MENSAJERIA)",
    "tipo_venta": "digital",
    "monto": 21.2
  },
  {
    "id": "457838a93f97361ca8509d67bc2781f66798f284",
    "fecha": "2022-12-30",
    "comercio": "APPLE",
    "giro_comercio": NaN,
    "tipo_venta": "fisica",
    "monto": 5.87
  },
  {
    "id": "457838a93f97361ca8509d67bc2781f66798f284",
    "fecha": "2022-12-30",
    "comercio": "UBER EATS",
    "giro_comercio": "TRASLADOS - FLETES, (SERVICIOS DE MENSAJERIA)",
    "tipo_venta": "digital",
    "monto": 38.5
  },
  {
    "id": "457838a93f97361ca8509d67bc2781f66798f284",
    "fecha": "2022-12-31",
    "comercio": "NETFLIX",
    "giro_comercio": "PAGO DE SERVICIO POR TELEVISION CABLE/POR EVENTO",
    "tipo_venta": "digital",
    "monto": 38.04
  },
  {
    "id": "457838a93f97361ca8509d67bc2781f66798f284",
    "fecha": "2023-01-01",
    "comercio": "APPLE",
    "giro_comercio": NaN,
    "tipo_venta": "fisica",
    "monto": 5.87
  },
  {
    "id": "457838a93f97361ca8509d67bc2781f66798f284",
    "fecha": "2023-01-01",
    "comercio": "DIDI FOOD",
    "giro_comercio": "COMIDA RAPIDA",
    "tipo_venta": "digital",
    "monto": 40.91
  },
  {
    "id": "457838a93f97361ca8509d67bc2781f66798f284",
    "fecha": "2023-01-02",
    "comercio": "NETFLIX",
    "giro_comercio": "PAGO DE SERVICIO POR TELEVISION CABLE/POR EVENTO",
    "tipo_venta": "digital",
    "monto": 38.04
  },
  {
    "id": "457838a93f97361ca8509d67bc2781f66798f284",
    "fecha": "2023-01-03",
    "comercio": "APPLE",
    "giro_comercio": NaN,
    "tipo_venta": "fisica",
    "monto": 5.87
  },
  {
    "id": "457838a93f97361ca8509d67bc2781f66798f284",
    "fecha": "2023-01-03",
    "comercio": "MERCADOPAGO",
    "giro_comercio": "MERCADO DIRECTO - VENTAS POR CATALOGO",
    "tipo_venta": "digital",
    "monto": 331.83
  },
  {
    "id": "457838a93f97361ca8509d67bc2781f66798f284",
    "fecha": "2023-01-03",
    "comercio": "OXXO",
    "giro_comercio": "TIENDAS DE CONVENIENCIA, MINISUPER",
    "tipo_venta": "fisica",
    "monto": 14.14
  },
  {
    "id": "457838a93f97361ca8509d67bc2781f66798f284",
    "fecha": "2023-01-04",
    "comercio": "NETFLIX",
    "giro_comercio": "PAGO DE SERVICIO POR TELEVISION CABLE/POR EVENTO",
    "tipo_venta": "digital",
    "monto": 38.04
  },
  {
    "id": "457838a93f97361ca8509d67bc2781f66798f284",
    "fecha": "2023-01-04",
    "comercio": "UBER EATS",
    "giro_comercio": "AGREGADOR",
    "tipo_venta": "digital",
    "monto": 23.23
  },
  {
    "id": "457838a93f97361ca8509d67bc2781f66798f284",
    "fecha": "2023-01-04",
    "comercio": "UBER EATS",
    "giro_comercio": "TRASLADOS - FLETES, (SERVICIOS DE MENSAJERIA)",
    "tipo_venta": "digital",
    "monto": 22.64
  },
  {
    "id": "457838a93f97361ca8509d67bc2781f66798f284",
    "fecha": "2023-01-04",
    "comercio": "MERCADO PAGO",
    "giro_comercio": "COMERCIOS ELECTRONICOS (VTAS POR INTERNET)",
    "tipo_venta": "digital",
    "monto": 37.59
  },
  {
    "id": "457838a93f97361ca8509d67bc2781f66798f284",
    "fecha": "2023-01-05",
    "comercio": "NETFLIX",
    "giro_comercio": "MERCADEO DIRECTO - NO CLASIFICADO",
    "tipo_venta": "digital",
    "monto": 38.04
  },
  {
    "id": "457838a93f97361ca8509d67bc2781f66798f284",
    "fecha": "2023-01-06",
    "comercio": "APPLE",
    "giro_comercio": NaN,
    "tipo_venta": "fisica",
    "monto": 5.87
  },
  {
    "id": "457838a93f97361ca8509d67bc2781f66798f284",
    "fecha": "2023-01-09",
    "comercio": "UBER",
    "giro_comercio": "AGREGADOR",
    "tipo_venta": "digital",
    "monto": 8.28
  },
  {
    "id": "457838a93f97361ca8509d67bc2781f66798f284",
    "fecha": "2023-01-10",
    "comercio": "OXXO",
    "giro_comercio": "TIENDAS DE CONVENIENCIA, MINISUPER",
    "tipo_venta": "fisica",
    "monto": 14.6
  },
  {
    "id": "457838a93f97361ca8509d67bc2781f66798f284",
    "fecha": "2023-01-11",
    "comercio": "AMAZON PRIME",
    "giro_comercio": "PAGO DE SERVICIO POR TELEVISION CABLE/POR EVENTO",
    "tipo_venta": "digital",
    "monto": 11.62
  },
  {
    "id": "457838a93f97361ca8509d67bc2781f66798f284",
    "fecha": "2023-01-11",
    "comercio": "UBER EATS",
    "giro_comercio": "TRASLADOS - FLETES, (SERVICIOS DE MENSAJERIA)",
    "tipo_venta": "digital",
    "monto": 25.65
  },
  {
    "id": "457838a93f97361ca8509d67bc2781f66798f284",
    "fecha": "2023-01-12",
    "comercio": "UBER EATS",
    "giro_comercio": "AGREGADOR",
    "tipo_venta": "digital",
    "monto": 40.68
  },
  {
    "id": "457838a93f97361ca8509d67bc2781f66798f284",
    "fecha": "2023-01-16",
    "comercio": "OXXO",
    "giro_comercio": "TIENDAS DE CONVENIENCIA, MINISUPER",
    "tipo_venta": "fisica",
    "monto": 17.01
  },
  {
    "id": "457838a93f97361ca8509d67bc2781f66798f284",
    "fecha": "2023-01-17",
    "comercio": "UBER EATS",
    "giro_comercio": "AGREGADOR",
    "tipo_venta": "digital",
    "monto": 25.09
  },
  {
    "id": "457838a93f97361ca8509d67bc2781f66798f284",
    "fecha": "2023-01-17",
    "comercio": "CHEDRAUI",
    "giro_comercio": "4121",
    "tipo_venta": "fisica",
    "monto": 103.92
  },
  {
    "id": "457838a93f97361ca8509d67bc2781f66798f284",
    "fecha": "2023-01-18",
    "comercio": "UBER EATS",
    "giro_comercio": "TRASLADOS - FLETES, (SERVICIOS DE MENSAJERIA)",
    "tipo_venta": "digital",
    "monto": 23.23
  },
  {
    "id": "457838a93f97361ca8509d67bc2781f66798f284",
    "fecha": "2023-01-19",
    "comercio": "SPOTIFY",
    "giro_comercio": "AGREGADOR",
    "tipo_venta": "digital",
    "monto": 23.1
  },
  {
    "id": "457838a93f97361ca8509d67bc2781f66798f284",
    "fecha": "2023-01-20",
    "comercio": "UBER EATS",
    "giro_comercio": "TRASLADOS - FLETES, (SERVICIOS DE MENSAJERIA)",
    "tipo_venta": "digital",
    "monto": 37.0
  },
  {
    "id": "457838a93f97361ca8509d67bc2781f66798f284",
    "fecha": "2023-01-20",
    "comercio": "WALMART",
    "giro_comercio": "4121",
    "tipo_venta": "fisica",
    "monto": 221.11
  },
  {
    "id": "457838a93f97361ca8509d67bc2781f66798f284",
    "fecha": "2023-01-21",
    "comercio": "APPLE",
    "giro_comercio": NaN,
    "tipo_venta": "fisica",
    "monto": 63.31
  },
  {
    "id": "457838a93f97361ca8509d67bc2781f66798f284",
    "fecha": "2023-01-21",
    "comercio": "AMAZON",
    "giro_comercio": "COMERCIOS ELECTRONICOS (VTAS POR INTERNET)",
    "tipo_venta": "digital",
    "monto": 2.54
  },
  {
    "id": "457838a93f97361ca8509d67bc2781f66798f284",
    "fecha": "2023-01-21",
    "comercio": "AMAZON",
    "giro_comercio": "COMERCIOS ELECTRONICOS (VTAS POR INTERNET)",
    "tipo_venta": "digital",
    "monto": 30.11
  },
  {
    "id": "457838a93f97361ca8509d67bc2781f66798f284",
    "fecha": "2023-01-21",
    "comercio": "AMAZON",
    "giro_comercio": "COMERCIOS ELECTRONICOS (VTAS POR INTERNET)",
    "tipo_venta": "digital",
    "monto": 15.06
  },
  {
    "id": "457838a93f97361ca8509d67bc2781f66798f284",
    "fecha": "2023-01-23",
    "comercio": "AMAZON",
    "giro_comercio": "COMERCIOS ELECTRONICOS (VTAS POR INTERNET)",
    "tipo_venta": "digital",
    "monto": 11.84
  },
  {
    "id": "457838a93f97361ca8509d67bc2781f66798f284",
    "fecha": "2023-01-23",
    "comercio": "AMAZON",
    "giro_comercio": "COMERCIOS ELECTRONICOS (VTAS POR INTERNET)",
    "tipo_venta": "digital",
    "monto": 26.55
  },
  {
    "id": "457838a93f97361ca8509d67bc2781f66798f284",
    "fecha": "2023-01-23",
    "comercio": "AMAZON",
    "giro_comercio": "COMERCIOS ELECTRONICOS (VTAS POR INTERNET)",
    "tipo_venta": "digital",
    "monto": 30.0
  },
  {
    "id": "457838a93f97361ca8509d67bc2781f66798f284",
    "fecha": "2023-01-24",
    "comercio": "APPLE",
    "giro_comercio": NaN,
    "tipo_venta": "fisica",
    "monto": 5.87
  },
  {
    "id": "457838a93f97361ca8509d67bc2781f66798f284",
    "fecha": "2023-01-24",
    "comercio": "APPLE",
    "giro_comercio": NaN,
    "tipo_venta": "fisica",
    "monto": 5.87
  },
  {
    "id": "457838a93f97361ca8509d67bc2781f66798f284",
    "fecha": "2023-01-25",
    "comercio": "APPLE",
    "giro_comercio": NaN,
    "tipo_venta": "fisica",
    "monto": 5.87
  },
  {
    "id": "457838a93f97361ca8509d67bc2781f66798f284",
    "fecha": "2023-01-25",
    "comercio": "MERCADO PAGO",
    "giro_comercio": "COMERCIOS ELECTRONICOS (VTAS POR INTERNET)",
    "tipo_venta": "digital",
    "monto": 36.52
  },
  {
    "id": "457838a93f97361ca8509d67bc2781f66798f284",
    "fecha": "2023-01-25",
    "comercio": "UBER EATS",
    "giro_comercio": "AGREGADOR",
    "tipo_venta": "digital",
    "monto": 25.65
  },
  {
    "id": "457838a93f97361ca8509d67bc2781f66798f284",
    "fecha": "2023-01-26",
    "comercio": "APPLE",
    "giro_comercio": NaN,
    "tipo_venta": "fisica",
    "monto": 5.87
  },
  {
    "id": "457838a93f97361ca8509d67bc2781f66798f284",
    "fecha": "2023-01-27",
    "comercio": "APPLE",
    "giro_comercio": NaN,
    "tipo_venta": "fisica",
    "monto": 5.87
  },
  {
    "id": "457838a93f97361ca8509d67bc2781f66798f284",
    "fecha": "2023-01-27",
    "comercio": "UBER EATS",
    "giro_comercio": "AGREGADOR",
    "tipo_venta": "digital",
    "monto": 24.94
  },
  {
    "id": "457838a93f97361ca8509d67bc2781f66798f284",
    "fecha": "2023-01-27",
    "comercio": "WALMART",
    "giro_comercio": "4121",
    "tipo_venta": "fisica",
    "monto": 273.2
  },
  {
    "id": "457838a93f97361ca8509d67bc2781f66798f284",
    "fecha": "2023-01-28",
    "comercio": "APPLE",
    "giro_comercio": NaN,
    "tipo_venta": "fisica",
    "monto": 63.31
  },
  {
    "id": "457838a93f97361ca8509d67bc2781f66798f284",
    "fecha": "2023-01-28",
    "comercio": "APPLE",
    "giro_comercio": NaN,
    "tipo_venta": "fisica",
    "monto": 5.87
  },
  {
    "id": "457838a93f97361ca8509d67bc2781f66798f284",
    "fecha": "2023-01-29",
    "comercio": "NETFLIX",
    "giro_comercio": "PAGO DE SERVICIO POR TELEVISION CABLE/POR EVENTO",
    "tipo_venta": "digital",
    "monto": 38.04
  },
  {
    "id": "457838a93f97361ca8509d67bc2781f66798f284",
    "fecha": "2023-01-29",
    "comercio": "NETFLIX",
    "giro_comercio": "PAGO DE SERVICIO POR TELEVISION CABLE/POR EVENTO",
    "tipo_venta": "digital",
    "monto": 38.04
  },
  {
    "id": "457838a93f97361ca8509d67bc2781f66798f284",
    "fecha": "2023-01-29",
    "comercio": "APPLE",
    "giro_comercio": NaN,
    "tipo_venta": "fisica",
    "monto": 5.87
  },
  {
    "id": "457838a93f97361ca8509d67bc2781f66798f284",
    "fecha": "2023-01-29",
    "comercio": "OXXO",
    "giro_comercio": "TIENDAS DE CONVENIENCIA, MINISUPER",
    "tipo_venta": "fisica",
    "monto": 12.99
  },
  {
    "id": "457838a93f97361ca8509d67bc2781f66798f284",
    "fecha": "2023-01-29",
    "comercio": "UBER EATS",
    "giro_comercio": "AGREGADOR",
    "tipo_venta": "digital",
    "monto": 25.15
  }
]