[
  {
    "id": "c548310f649be29ffac0f04ca50a0bd0ed9a3352",
    "fecha": "2022-01-07",
    "comercio": "ITUNES",
    "giro_comercio": "AGREGADOR",
    "tipo_venta": "digital",
    "monto": 23.1
  },
  {
    "id": "c548310f649be29ffac0f04ca50a0bd0ed9a3352",
    "fecha": "2022-01-08",
    "comercio": "RENTAMOVISTAR",
    "giro_comercio": "AGREGADOR",
    "tipo_venta": "digital",
    "monto": 30.46
  },
  {
    "id": "c548310f649be29ffac0f04ca50a0bd0ed9a3352",
    "fecha": "2022-01-09",
    "comercio": "GOOGLE",
    "giro_comercio": "AGREGADOR",
    "tipo_venta": "digital",
    "monto": 4.15
  },
  {
    "id": "c548310f649be29ffac0f04ca50a0bd0ed9a3352",
    "fecha": "2022-01-11",
    "comercio": "TOTAL PLAY",
    "giro_comercio": "SERVICIOS DE TELECOMUNICACION, LLAMADAS LOC Y LARG",
    "tipo_venta": "digital",
    "monto": 90.88
  },
  {
    "id": "c548310f649be29ffac0f04ca50a0bd0ed9a3352",
    "fecha": "2022-01-11",
    "comercio": "MICROSOFT",
    "giro_comercio": "AGREGADOR",
    "tipo_venta": "digital",
    "monto": 4.72
  },
  {
    "id": "c548310f649be29ffac0f04ca50a0bd0ed9a3352",
    "fecha": "2022-01-15",
    "comercio": "MERCADO PAGO",
    "giro_comercio": "MERCADO DIRECTO - VENTAS POR CATALOGO",
    "tipo_venta": "digital",
    "monto": 31.77
  },
  {
    "id": "c548310f649be29ffac0f04ca50a0bd0ed9a3352",
    "fecha": "2022-01-18",
    "comercio": "CINEPOLIS",
    "giro_comercio": "CINES, TEATROS",
    "tipo_venta": "fisica",
    "monto": 74.68
  },
  {
    "id": "c548310f649be29ffac0f04ca50a0bd0ed9a3352",
    "fecha": "2022-01-21",
    "comercio": "UBER",
    "giro_comercio": "LIMOSINAS, (TAXIS)",
    "tipo_venta": "fisica",
    "monto": 24.36
  },
  {
    "id": "c548310f649be29ffac0f04ca50a0bd0ed9a3352",
    "fecha": "2022-01-21",
    "comercio": "UBER",
    "giro_comercio": "LIMOSINAS, (TAXIS)",
    "tipo_venta": "fisica",
    "monto": 9.76
  },
  {
    "id": "c548310f649be29ffac0f04ca50a0bd0ed9a3352",
    "fecha": "2022-01-21",
    "comercio": "UBER",
    "giro_comercio": "LIMOSINAS, (TAXIS)",
    "tipo_venta": "fisica",
    "monto": 9.42
  },
  {
    "id": "c548310f649be29ffac0f04ca50a0bd0ed9a3352",
    "fecha": "2022-01-21",
    "comercio": "UBER",
    "giro_comercio": "LIMOSINAS, (TAXIS)",
    "tipo_venta": "fisica",
    "monto": 33.56
  },
  {
    "id": "c548310f649be29ffac0f04ca50a0bd0ed9a3352",
    "fecha": "2022-01-22",
    "comercio": "ITUNES",
    "giro_comercio": "AGREGADOR",
    "tipo_venta": "digital",
    "monto": 28.85
  },
  {
    "id": "c548310f649be29ffac0f04ca50a0bd0ed9a3352",
    "fecha": "2022-01-22",
    "comercio": "TOTALPLAY",
    "giro_comercio": "SERVICIOS DE TELECOMUNICACION, LLAMADAS LOC Y LARG",
    "tipo_venta": "digital",
    "monto": 79.4
  },
  {
    "id": "c548310f649be29ffac0f04ca50a0bd0ed9a3352",
    "fecha": "2022-01-23",
    "comercio": "WALMART",
    "giro_comercio": "AGREGADOR",
    "tipo_venta": "digital",
    "monto": 197.66
  },
  {
    "id": "c548310f649be29ffac0f04ca50a0bd0ed9a3352",
    "fecha": "2022-01-23",
    "comercio": "WALMART",
    "giro_comercio": "AGREGADOR",
    "tipo_venta": "digital",
    "monto": 197.66
  },
  {
    "id": "c548310f649be29ffac0f04ca50a0bd0ed9a3352",
    "fecha": "2022-01-23",
    "comercio": "CFE",
    "giro_comercio": "SERV GUBERNAM, AGUA, ELECTRICIDAD,PREDIAL,TENENCIA",
    "tipo_venta": "digital",
    "monto": 128.91
  },
  {
    "id": "c548310f649be29ffac0f04ca50a0bd0ed9a3352",
    "fecha": "2022-01-24",
    "comercio": "CINEPOLIS",
    "giro_comercio": "AGREGADOR",
    "tipo_venta": "digital",
    "monto": 77.44
  },
  {
    "id": "c548310f649be29ffac0f04ca50a0bd0ed9a3352",
    "fecha": "2022-01-26",
    "comercio": "ITUNES",
    "giro_comercio": "AGREGADOR",
    "tipo_venta": "digital",
    "monto": 1.96
  },
  {
    "id": "c548310f649be29ffac0f04ca50a0bd0ed9a3352",
    "fecha": "2022-01-30",
    "comercio": "TELEFONICA",
    "giro_comercio": "SERVICIOS DE TELECOMUNICACION, LLAMADAS LOC Y LARG",
    "tipo_venta": "digital",
    "monto": 32.29
  },
  {
    "id": "c548310f649be29ffac0f04ca50a0bd0ed9a3352",
    "fecha": "2022-01-31",
    "comercio": "AMAZON",
    "giro_comercio": "COMERCIOS ELECTRONICOS (VTAS POR INTERNET)",
    "tipo_venta": "digital",
    "monto": 59.01
  },
  {
    "id": "c548310f649be29ffac0f04ca50a0bd0ed9a3352",
    "fecha": "2022-01-31",
    "comercio": "AMAZON",
    "giro_comercio": "COMERCIOS ELECTRONICOS (VTAS POR INTERNET)",
    "tipo_venta": "digital",
    "monto": 58.26
  },
  {
    "id": "c548310f649be29ffac0f04ca50a0bd0ed9a3352",
    "fecha": "2022-02-08",
    "comercio": "CFE",
    "giro_comercio": "SERV GUBERNAM, AGUA, ELECTRICIDAD,PREDIAL,TENENCIA",
    "tipo_venta": "digital",
    "monto": 25.75
  },
  {
    "id": "c548310f649be29ffac0f04ca50a0bd0ed9a3352",
    "fecha": "2022-02-08",
    "comercio": "CFE",
    "giro_comercio": "SERV GUBERNAM, AGUA, ELECTRICIDAD,PREDIAL,TENENCIA",
    "tipo_venta": "digital",
    "monto": 17.59
  },
  {
    "id": "c548310f649be29ffac0f04ca50a0bd0ed9a3352",
    "fecha": "2022-02-08",
    "comercio": "CFE",
    "giro_comercio": "SERV GUBERNAM, AGUA, ELECTRICIDAD,PREDIAL,TENENCIA",
    "tipo_venta": "digital",
    "monto": 8.28
  },
  {
    "id": "c548310f649be29ffac0f04ca50a0bd0ed9a3352",
    "fecha": "2022-02-08",
    "comercio": "ITUNES",
    "giro_comercio": "AGREGADOR",
    "tipo_venta": "digital",
    "monto": 23.1
  },
  {
    "id": "c548310f649be29ffac0f04ca50a0bd0ed9a3352",
    "fecha": "2022-02-08",
    "comercio": "ITUNES",
    "giro_comercio": "AGREGADOR",
    "tipo_venta": "digital",
    "monto": 23.1
  },
  {
    "id": "c548310f649be29ffac0f04ca50a0bd0ed9a3352",
    "fecha": "2022-02-11",
    "comercio": "TOTAL PLAY",
    "giro_comercio": "SERVICIOS DE TELECOMUNICACION, LLAMADAS LOC Y LARG",
    "tipo_venta": "digital",
    "monto": 90.88
  },
  {
    "id": "c548310f649be29ffac0f04ca50a0bd0ed9a3352",
    "fecha": "2022-02-11",
    "comercio": "MICROSOFT",
    "giro_comercio": "AGREGADOR",
    "tipo_venta": "digital",
    "monto": 4.72
  },
  {
    "id": "c548310f649be29ffac0f04ca50a0bd0ed9a3352",
    "fecha": "2022-02-13",
    "comercio": "AMAZON",
    "giro_comercio": "COMERCIOS ELECTRONICOS (VTAS POR INTERNET)",
    "tipo_venta": "digital",
    "monto": 434.47
  },
  {
    "id": "c548310f649be29ffac0f04ca50a0bd0ed9a3352",
    "fecha": "2022-02-14",
    "comercio": "RAPPI",
    "giro_comercio": "AGREGADOR",
    "tipo_venta": "digital",
    "monto": 16.42
  },
  {
    "id": "c548310f649be29ffac0f04ca50a0bd0ed9a3352",
    "fecha": "2022-02-21",
    "comercio": "WALMART",
    "giro_comercio": "AGREGADOR",
    "tipo_venta": "digital",
    "monto": 53.82
  },
  {
    "id": "c548310f649be29ffac0f04ca50a0bd0ed9a3352",
    "fecha": "2022-02-22",
    "comercio": "ITUNES",
    "giro_comercio": "AGREGADOR",
    "tipo_venta": "digital",
    "monto": 28.85
  },
  {
    "id": "c548310f649be29ffac0f04ca50a0bd0ed9a3352",
    "fecha": "2022-02-26",
    "comercio": "AMAZON",
    "giro_comercio": "COMERCIOS ELECTRONICOS (VTAS POR INTERNET)",
    "tipo_venta": "digital",
    "monto": 80.77
  },
  {
    "id": "c548310f649be29ffac0f04ca50a0bd0ed9a3352",
    "fecha": "2022-02-28",
    "comercio": "ITUNES",
    "giro_comercio": "AGREGADOR",
    "tipo_venta": "digital",
    "monto": 40.34
  },
  {
    "id": "c548310f649be29ffac0f04ca50a0bd0ed9a3352",
    "fecha": "2022-03-01",
    "comercio": "TELEFONICA",
    "giro_comercio": "SERVICIOS DE TELECOMUNICACION, LLAMADAS LOC Y LARG",
    "tipo_venta": "digital",
    "monto": 32.29
  },
  {
    "id": "c548310f649be29ffac0f04ca50a0bd0ed9a3352",
    "fecha": "2022-03-06",
    "comercio": "CINEPOLIS",
    "giro_comercio": "AGREGADOR",
    "tipo_venta": "digital",
    "monto": 38.84
  },
  {
    "id": "c548310f649be29ffac0f04ca50a0bd0ed9a3352",
    "fecha": "2022-03-07",
    "comercio": "ITUNES",
    "giro_comercio": "AGREGADOR",
    "tipo_venta": "digital",
    "monto": 23.1
  },
  {
    "id": "c548310f649be29ffac0f04ca50a0bd0ed9a3352",
    "fecha": "2022-03-11",
    "comercio": "TOTAL PLAY",
    "giro_comercio": "SERVICIOS DE TELECOMUNICACION, LLAMADAS LOC Y LARG",
    "tipo_venta": "digital",
    "monto": 90.88
  },
  {
    "id": "c548310f649be29ffac0f04ca50a0bd0ed9a3352",
    "fecha": "2022-03-11",
    "comercio": "AMAZON",
    "giro_comercio": "COMERCIOS ELECTRONICOS (VTAS POR INTERNET)",
    "tipo_venta": "digital",
    "monto": 35.05
  },
  {
    "id": "c548310f649be29ffac0f04ca50a0bd0ed9a3352",
    "fecha": "2022-03-11",
    "comercio": "MICROSOFT",
    "giro_comercio": "AGREGADOR",
    "tipo_venta": "digital",
    "monto": 4.72
  },
  {
    "id": "c548310f649be29ffac0f04ca50a0bd0ed9a3352",
    "fecha": "2022-03-12",
    "comercio": "AMAZON",
    "giro_comercio": "COMERCIOS ELECTRONICOS (VTAS POR INTERNET)",
    "tipo_venta": "digital",
    "monto": 17.12
  },
  {
    "id": "c548310f649be29ffac0f04ca50a0bd0ed9a3352",
    "fecha": "2022-03-12",
    "comercio": "AMAZON",
    "giro_comercio": "COMERCIOS ELECTRONICOS (VTAS POR INTERNET)",
    "tipo_venta": "digital",
    "monto": 727.85
  },
  {
    "id": "c548310f649be29ffac0f04ca50a0bd0ed9a3352",
    "fecha": "2022-03-13",
    "comercio": "TOTALPLAY",
    "giro_comercio": "SERVICIOS DE TELECOMUNICACION, LLAMADAS LOC Y LARG",
    "tipo_venta": "digital",
    "monto": 85.14
  },
  {
    "id": "c548310f649be29ffac0f04ca50a0bd0ed9a3352",
    "fecha": "2022-03-13",
    "comercio": "WALMART",
    "giro_comercio": "AGREGADOR",
    "tipo_venta": "digital",
    "monto": 84.16
  },
  {
    "id": "c548310f649be29ffac0f04ca50a0bd0ed9a3352",
    "fecha": "2022-03-14",
    "comercio": "AMAZON",
    "giro_comercio": "COMERCIOS ELECTRONICOS (VTAS POR INTERNET)",
    "tipo_venta": "digital",
    "monto": 8.14
  },
  {
    "id": "c548310f649be29ffac0f04ca50a0bd0ed9a3352",
    "fecha": "2022-03-18",
    "comercio": "AMAZON",
    "giro_comercio": "COMERCIOS ELECTRONICOS (VTAS POR INTERNET)",
    "tipo_venta": "digital",
    "monto": 43.99
  },
  {
    "id": "c548310f649be29ffac0f04ca50a0bd0ed9a3352",
    "fecha": "2022-03-20",
    "comercio": "AMAZON",
    "giro_comercio": "COMERCIOS ELECTRONICOS (VTAS POR INTERNET)",
    "tipo_venta": "digital",
    "monto": 294.77
  },
  {
    "id": "c548310f649be29ffac0f04ca50a0bd0ed9a3352",
    "fecha": "2022-03-20",
    "comercio": "TELCEL",
    "giro_comercio": "SERVICIOS EMPRESARIALES - NO CLASIFICADOS",
    "tipo_venta": "digital",
    "monto": 11.73
  },
  {
    "id": "c548310f649be29ffac0f04ca50a0bd0ed9a3352",
    "fecha": "2022-03-22",
    "comercio": "ITUNES",
    "giro_comercio": "AGREGADOR",
    "tipo_venta": "digital",
    "monto": 28.85
  },
  {
    "id": "c548310f649be29ffac0f04ca50a0bd0ed9a3352",
    "fecha": "2022-03-22",
    "comercio": "TOTALPLAY",
    "giro_comercio": "SERVICIOS DE TELECOMUNICACION, LLAMADAS LOC Y LARG",
    "tipo_venta": "digital",
    "monto": 79.4
  },
  {
    "id": "c548310f649be29ffac0f04ca50a0bd0ed9a3352",
    "fecha": "2022-03-22",
    "comercio": "AMAZON",
    "giro_comercio": "COMERCIOS ELECTRONICOS (VTAS POR INTERNET)",
    "tipo_venta": "digital",
    "monto": 42.75
  },
  {
    "id": "c548310f649be29ffac0f04ca50a0bd0ed9a3352",
    "fecha": "2022-03-22",
    "comercio": "AMAZON",
    "giro_comercio": "COMERCIOS ELECTRONICOS (VTAS POR INTERNET)",
    "tipo_venta": "digital",
    "monto": 99.28
  },
  {
    "id": "c548310f649be29ffac0f04ca50a0bd0ed9a3352",
    "fecha": "2022-03-25",
    "comercio": "CFE",
    "giro_comercio": "SERV GUBERNAM, AGUA, ELECTRICIDAD,PREDIAL,TENENCIA",
    "tipo_venta": "digital",
    "monto": 94.44
  },
  {
    "id": "c548310f649be29ffac0f04ca50a0bd0ed9a3352",
    "fecha": "2022-03-27",
    "comercio": "ITUNES",
    "giro_comercio": "AGREGADOR",
    "tipo_venta": "digital",
    "monto": 8.17
  },
  {
    "id": "c548310f649be29ffac0f04ca50a0bd0ed9a3352",
    "fecha": "2022-03-28",
    "comercio": "UBER",
    "giro_comercio": "LIMOSINAS, (TAXIS)",
    "tipo_venta": "fisica",
    "monto": 9.42
  },
  {
    "id": "c548310f649be29ffac0f04ca50a0bd0ed9a3352",
    "fecha": "2022-03-28",
    "comercio": "UBER",
    "giro_comercio": "LIMOSINAS, (TAXIS)",
    "tipo_venta": "fisica",
    "monto": 10.58
  },
  {
    "id": "c548310f649be29ffac0f04ca50a0bd0ed9a3352",
    "fecha": "2022-03-30",
    "comercio": "UBER",
    "giro_comercio": "LIMOSINAS, (TAXIS)",
    "tipo_venta": "fisica",
    "monto": 12.13
  },
  {
    "id": "c548310f649be29ffac0f04ca50a0bd0ed9a3352",
    "fecha": "2022-03-31",
    "comercio": "UBER",
    "giro_comercio": "LIMOSINAS, (TAXIS)",
    "tipo_venta": "fisica",
    "monto": 41.65
  },
  {
    "id": "c548310f649be29ffac0f04ca50a0bd0ed9a3352",
    "fecha": "2022-04-02",
    "comercio": "UBER",
    "giro_comercio": "AGREGADOR",
    "tipo_venta": "digital",
    "monto": 42.72
  },
  {
    "id": "c548310f649be29ffac0f04ca50a0bd0ed9a3352",
    "fecha": "2022-04-02",
    "comercio": "RENTAMOVISTAR",
    "giro_comercio": "AGREGADOR",
    "tipo_venta": "digital",
    "monto": 32.29
  },
  {
    "id": "c548310f649be29ffac0f04ca50a0bd0ed9a3352",
    "fecha": "2022-04-06",
    "comercio": "ITUNES",
    "giro_comercio": "AGREGADOR",
    "tipo_venta": "digital",
    "monto": 23.1
  },
  {
    "id": "c548310f649be29ffac0f04ca50a0bd0ed9a3352",
    "fecha": "2022-04-09",
    "comercio": "CFE",
    "giro_comercio": "SERV GUBERNAM, AGUA, ELECTRICIDAD,PREDIAL,TENENCIA",
    "tipo_venta": "digital",
    "monto": 36.77
  },
  {
    "id": "c548310f649be29ffac0f04ca50a0bd0ed9a3352",
    "fecha": "2022-04-09",
    "comercio": "CFE",
    "giro_comercio": "SERV GUBERNAM, AGUA, ELECTRICIDAD,PREDIAL,TENENCIA",
    "tipo_venta": "digital",
    "monto": 25.4
  },
  {
    "id": "c548310f649be29ffac0f04ca50a0bd0ed9a3352",
    "fecha": "2022-04-09",
    "comercio": "CFE",
    "giro_comercio": "SERV GUBERNAM, AGUA, ELECTRICIDAD,PREDIAL,TENENCIA",
    "tipo_venta": "digital",
    "monto": 16.1
  },
  {
    "id": "c548310f649be29ffac0f04ca50a0bd0ed9a3352",
    "fecha": "2022-04-11",
    "comercio": "AMAZON",
    "giro_comercio": "COMERCIOS ELECTRONICOS (VTAS POR INTERNET)",
    "tipo_venta": "digital",
    "monto": 5.99
  },
  {
    "id": "c548310f649be29ffac0f04ca50a0bd0ed9a3352",
    "fecha": "2022-04-11",
    "comercio": "TOTAL PLAY",
    "giro_comercio": "SERVICIOS DE TELECOMUNICACION, LLAMADAS LOC Y LARG",
    "tipo_venta": "digital",
    "monto": 90.88
  },
  {
    "id": "c548310f649be29ffac0f04ca50a0bd0ed9a3352",
    "fecha": "2022-04-12",
    "comercio": "MICROSOFT",
    "giro_comercio": "AGREGADOR",
    "tipo_venta": "digital",
    "monto": 4.72
  },
  {
    "id": "c548310f649be29ffac0f04ca50a0bd0ed9a3352",
    "fecha": "2022-04-19",
    "comercio": "AMAZON",
    "giro_comercio": "COMERCIOS ELECTRONICOS (VTAS POR INTERNET)",
    "tipo_venta": "digital",
    "monto": 163.6
  },
  {
    "id": "c548310f649be29ffac0f04ca50a0bd0ed9a3352",
    "fecha": "2022-04-21",
    "comercio": "AMAZON",
    "giro_comercio": "COMERCIOS ELECTRONICOS (VTAS POR INTERNET)",
    "tipo_venta": "digital",
    "monto": 62.01
  },
  {
    "id": "c548310f649be29ffac0f04ca50a0bd0ed9a3352",
    "fecha": "2022-04-21",
    "comercio": "AMAZON",
    "giro_comercio": "COMERCIOS ELECTRONICOS (VTAS POR INTERNET)",
    "tipo_venta": "digital",
    "monto": 70.32
  },
  {
    "id": "c548310f649be29ffac0f04ca50a0bd0ed9a3352",
    "fecha": "2022-04-22",
    "comercio": "ITUNES",
    "giro_comercio": "AGREGADOR",
    "tipo_venta": "digital",
    "monto": 28.85
  },
  {
    "id": "c548310f649be29ffac0f04ca50a0bd0ed9a3352",
    "fecha": "2022-04-24",
    "comercio": "WALMART",
    "giro_comercio": "AGREGADOR",
    "tipo_venta": "digital",
    "monto": 92.26
  },
  {
    "id": "c548310f649be29ffac0f04ca50a0bd0ed9a3352",
    "fecha": "2022-04-25",
    "comercio": "AMAZON",
    "giro_comercio": "COMERCIOS ELECTRONICOS (VTAS POR INTERNET)",
    "tipo_venta": "digital",
    "monto": 137.99
  },
  {
    "id": "c548310f649be29ffac0f04ca50a0bd0ed9a3352",
    "fecha": "2022-04-25",
    "comercio": "AMAZON",
    "giro_comercio": "COMERCIOS ELECTRONICOS (VTAS POR INTERNET)",
    "tipo_venta": "digital",
    "monto": 15.52
  },
  {
    "id": "c548310f649be29ffac0f04ca50a0bd0ed9a3352",
    "fecha": "2022-04-28",
    "comercio": "AMAZON",
    "giro_comercio": "COMERCIOS ELECTRONICOS (VTAS POR INTERNET)",
    "tipo_venta": "digital",
    "monto": 147.05
  },
  {
    "id": "c548310f649be29ffac0f04ca50a0bd0ed9a3352",
    "fecha": "2022-04-28",
    "comercio": "AMAZON",
    "giro_comercio": "COMERCIOS ELECTRONICOS (VTAS POR INTERNET)",
    "tipo_venta": "digital",
    "monto": 410.76
  },
  {
    "id": "c548310f649be29ffac0f04ca50a0bd0ed9a3352",
    "fecha": "2022-04-28",
    "comercio": "AMAZON",
    "giro_comercio": "COMERCIOS ELECTRONICOS (VTAS POR INTERNET)",
    "tipo_venta": "digital",
    "monto": 23.1
  },
  {
    "id": "c548310f649be29ffac0f04ca50a0bd0ed9a3352",
    "fecha": "2022-04-29",
    "comercio": "AMAZON",
    "giro_comercio": "COMERCIOS ELECTRONICOS (VTAS POR INTERNET)",
    "tipo_venta": "digital",
    "monto": 222.67
  },
  {
    "id": "c548310f649be29ffac0f04ca50a0bd0ed9a3352",
    "fecha": "2022-04-29",
    "comercio": "AMAZON",
    "giro_comercio": "COMERCIOS ELECTRONICOS (VTAS POR INTERNET)",
    "tipo_venta": "digital",
    "monto": 67.81
  },
  {
    "id": "c548310f649be29ffac0f04ca50a0bd0ed9a3352",
    "fecha": "2022-04-29",
    "comercio": "AMAZON",
    "giro_comercio": "COMERCIOS ELECTRONICOS (VTAS POR INTERNET)",
    "tipo_venta": "digital",
    "monto": 23.1
  },
  {
    "id": "c548310f649be29ffac0f04ca50a0bd0ed9a3352",
    "fecha": "2022-04-30",
    "comercio": "WALMART",
    "giro_comercio": "AGREGADOR",
    "tipo_venta": "digital",
    "monto": 70.78
  },
  {
    "id": "c548310f649be29ffac0f04ca50a0bd0ed9a3352",
    "fecha": "2022-04-30",
    "comercio": "TOTALPLAY",
    "giro_comercio": "AGREGADOR",
    "tipo_venta": "digital",
    "monto": 79.4
  },
  {
    "id": "c548310f649be29ffac0f04ca50a0bd0ed9a3352",
    "fecha": "2022-05-06",
    "comercio": "WALMART",
    "giro_comercio": "AGREGADOR",
    "tipo_venta": "digital",
    "monto": 139.42
  },
  {
    "id": "c548310f649be29ffac0f04ca50a0bd0ed9a3352",
    "fecha": "2022-05-08",
    "comercio": "AMAZON",
    "giro_comercio": "COMERCIOS ELECTRONICOS (VTAS POR INTERNET)",
    "tipo_venta": "digital",
    "monto": 78.25
  },
  {
    "id": "c548310f649be29ffac0f04ca50a0bd0ed9a3352",
    "fecha": "2022-05-10",
    "comercio": "ITUNES",
    "giro_comercio": "AGREGADOR",
    "tipo_venta": "digital",
    "monto": 23.1
  },
  {
    "id": "c548310f649be29ffac0f04ca50a0bd0ed9a3352",
    "fecha": "2022-05-10",
    "comercio": "ITUNES",
    "giro_comercio": "AGREGADOR",
    "tipo_venta": "digital",
    "monto": 40.34
  },
  {
    "id": "c548310f649be29ffac0f04ca50a0bd0ed9a3352",
    "fecha": "2022-05-11",
    "comercio": "AMAZON",
    "giro_comercio": "COMERCIOS ELECTRONICOS (VTAS POR INTERNET)",
    "tipo_venta": "digital",
    "monto": 5.99
  },
  {
    "id": "c548310f649be29ffac0f04ca50a0bd0ed9a3352",
    "fecha": "2022-05-11",
    "comercio": "TOTAL PLAY",
    "giro_comercio": "SERVICIOS DE TELECOMUNICACION, LLAMADAS LOC Y LARG",
    "tipo_venta": "digital",
    "monto": 90.88
  },
  {
    "id": "c548310f649be29ffac0f04ca50a0bd0ed9a3352",
    "fecha": "2022-05-13",
    "comercio": "MICROSOFT",
    "giro_comercio": "AGREGADOR",
    "tipo_venta": "digital",
    "monto": 4.72
  },
  {
    "id": "c548310f649be29ffac0f04ca50a0bd0ed9a3352",
    "fecha": "2022-05-16",
    "comercio": "TOTAL PLAY",
    "giro_comercio": "SERVICIOS DE TELECOMUNICACION, LLAMADAS LOC Y LARG",
    "tipo_venta": "digital",
    "monto": 90.88
  },
  {
    "id": "c548310f649be29ffac0f04ca50a0bd0ed9a3352",
    "fecha": "2022-05-22",
    "comercio": "ITUNES",
    "giro_comercio": "AGREGADOR",
    "tipo_venta": "digital",
    "monto": 28.85
  },
  {
    "id": "c548310f649be29ffac0f04ca50a0bd0ed9a3352",
    "fecha": "2022-05-22",
    "comercio": "CFE",
    "giro_comercio": "SERV GUBERNAM, AGUA, ELECTRICIDAD,PREDIAL,TENENCIA",
    "tipo_venta": "digital",
    "monto": 174.52
  },
  {
    "id": "c548310f649be29ffac0f04ca50a0bd0ed9a3352",
    "fecha": "2022-05-23",
    "comercio": "AMAZON",
    "giro_comercio": "COMERCIOS ELECTRONICOS (VTAS POR INTERNET)",
    "tipo_venta": "digital",
    "monto": 378.19
  },
  {
    "id": "c548310f649be29ffac0f04ca50a0bd0ed9a3352",
    "fecha": "2022-05-24",
    "comercio": "TOTALPLAY",
    "giro_comercio": "SERVICIOS DE TELECOMUNICACION, LLAMADAS LOC Y LARG",
    "tipo_venta": "digital",
    "monto": 79.4
  },
  {
    "id": "c548310f649be29ffac0f04ca50a0bd0ed9a3352",
    "fecha": "2022-05-25",
    "comercio": "WALMART",
    "giro_comercio": "AGREGADOR",
    "tipo_venta": "digital",
    "monto": 97.37
  },
  {
    "id": "c548310f649be29ffac0f04ca50a0bd0ed9a3352",
    "fecha": "2022-05-28",
    "comercio": "AMAZON",
    "giro_comercio": "COMERCIOS ELECTRONICOS (VTAS POR INTERNET)",
    "tipo_venta": "digital",
    "monto": 37.35
  },
  {
    "id": "c548310f649be29ffac0f04ca50a0bd0ed9a3352",
    "fecha": "2022-06-07",
    "comercio": "AMAZON PRIME",
    "giro_comercio": "PAGO DE SERVICIO POR TELEVISION CABLE/POR EVENTO",
    "tipo_venta": "digital",
    "monto": 103.52
  },
  {
    "id": "c548310f649be29ffac0f04ca50a0bd0ed9a3352",
    "fecha": "2022-06-07",
    "comercio": "ITUNES",
    "giro_comercio": "AGREGADOR",
    "tipo_venta": "digital",
    "monto": 30.0
  },
  {
    "id": "c548310f649be29ffac0f04ca50a0bd0ed9a3352",
    "fecha": "2022-06-07",
    "comercio": "ITUNES",
    "giro_comercio": "AGREGADOR",
    "tipo_venta": "digital",
    "monto": 30.0
  },
  {
    "id": "c548310f649be29ffac0f04ca50a0bd0ed9a3352",
    "fecha": "2022-06-10",
    "comercio": "RENTAMOVISTAR",
    "giro_comercio": "AGREGADOR",
    "tipo_venta": "digital",
    "monto": 32.29
  },
  {
    "id": "c548310f649be29ffac0f04ca50a0bd0ed9a3352",
    "fecha": "2022-06-10",
    "comercio": "CFE",
    "giro_comercio": "SERV GUBERNAM, AGUA, ELECTRICIDAD,PREDIAL,TENENCIA",
    "tipo_venta": "digital",
    "monto": 35.51
  },
  {
    "id": "c548310f649be29ffac0f04ca50a0bd0ed9a3352",
    "fecha": "2022-06-10",
    "comercio": "CFE",
    "giro_comercio": "SERV GUBERNAM, AGUA, ELECTRICIDAD,PREDIAL,TENENCIA",
    "tipo_venta": "digital",
    "monto": 40.56
  },
  {
    "id": "c548310f649be29ffac0f04ca50a0bd0ed9a3352",
    "fecha": "2022-06-10",
    "comercio": "ITUNES",
    "giro_comercio": "AGREGADOR",
    "tipo_venta": "digital",
    "monto": 40.34
  },
  {
    "id": "c548310f649be29ffac0f04ca50a0bd0ed9a3352",
    "fecha": "2022-06-10",
    "comercio": "ITUNES",
    "giro_comercio": "AGREGADOR",
    "tipo_venta": "digital",
    "monto": 40.34
  },
  {
    "id": "c548310f649be29ffac0f04ca50a0bd0ed9a3352",
    "fecha": "2022-06-11",
    "comercio": "AMAZON",
    "giro_comercio": "COMERCIOS ELECTRONICOS (VTAS POR INTERNET)",
    "tipo_venta": "digital",
    "monto": 5.99
  },
  {
    "id": "c548310f649be29ffac0f04ca50a0bd0ed9a3352",
    "fecha": "2022-06-11",
    "comercio": "TOTAL PLAY",
    "giro_comercio": "SERVICIOS DE TELECOMUNICACION, LLAMADAS LOC Y LARG",
    "tipo_venta": "digital",
    "monto": 93.18
  },
  {
    "id": "c548310f649be29ffac0f04ca50a0bd0ed9a3352",
    "fecha": "2022-06-16",
    "comercio": "TOTAL PLAY",
    "giro_comercio": "SERVICIOS DE TELECOMUNICACION, LLAMADAS LOC Y LARG",
    "tipo_venta": "digital",
    "monto": 93.18
  },
  {
    "id": "c548310f649be29ffac0f04ca50a0bd0ed9a3352",
    "fecha": "2022-06-19",
    "comercio": "TOTAL PLAY",
    "giro_comercio": "SERVICIOS DE TELECOMUNICACION, LLAMADAS LOC Y LARG",
    "tipo_venta": "digital",
    "monto": 93.18
  },
  {
    "id": "c548310f649be29ffac0f04ca50a0bd0ed9a3352",
    "fecha": "2022-06-19",
    "comercio": "WALMART",
    "giro_comercio": "AGREGADOR",
    "tipo_venta": "digital",
    "monto": 137.51
  },
  {
    "id": "c548310f649be29ffac0f04ca50a0bd0ed9a3352",
    "fecha": "2022-06-19",
    "comercio": "WALMART",
    "giro_comercio": "AGREGADOR",
    "tipo_venta": "digital",
    "monto": 137.51
  },
  {
    "id": "c548310f649be29ffac0f04ca50a0bd0ed9a3352",
    "fecha": "2022-06-21",
    "comercio": "AMAZON",
    "giro_comercio": "COMERCIOS ELECTRONICOS (VTAS POR INTERNET)",
    "tipo_venta": "digital",
    "monto": 870.12
  },
  {
    "id": "c548310f649be29ffac0f04ca50a0bd0ed9a3352",
    "fecha": "2022-06-21",
    "comercio": "AMAZON",
    "giro_comercio": "COMERCIOS ELECTRONICOS (VTAS POR INTERNET)",
    "tipo_venta": "digital",
    "monto": 58.89
  },
  {
    "id": "c548310f649be29ffac0f04ca50a0bd0ed9a3352",
    "fecha": "2022-06-21",
    "comercio": "AMAZON",
    "giro_comercio": "COMERCIOS ELECTRONICOS (VTAS POR INTERNET)",
    "tipo_venta": "digital",
    "monto": 870.12
  },
  {
    "id": "c548310f649be29ffac0f04ca50a0bd0ed9a3352",
    "fecha": "2022-06-21",
    "comercio": "AMAZON",
    "giro_comercio": "COMERCIOS ELECTRONICOS (VTAS POR INTERNET)",
    "tipo_venta": "digital",
    "monto": 870.12
  },
  {
    "id": "c548310f649be29ffac0f04ca50a0bd0ed9a3352",
    "fecha": "2022-06-22",
    "comercio": "TOTAL PLAY",
    "giro_comercio": "SERVICIOS DE TELECOMUNICACION, LLAMADAS LOC Y LARG",
    "tipo_venta": "digital",
    "monto": 98.93
  },
  {
    "id": "c548310f649be29ffac0f04ca50a0bd0ed9a3352",
    "fecha": "2022-06-24",
    "comercio": "TOTALPLAY",
    "giro_comercio": "SERVICIOS DE TELECOMUNICACION, LLAMADAS LOC Y LARG",
    "tipo_venta": "digital",
    "monto": 82.84
  },
  {
    "id": "c548310f649be29ffac0f04ca50a0bd0ed9a3352",
    "fecha": "2022-06-25",
    "comercio": "TOTAL PLAY",
    "giro_comercio": "SERVICIOS DE TELECOMUNICACION, LLAMADAS LOC Y LARG",
    "tipo_venta": "digital",
    "monto": 98.93
  },
  {
    "id": "c548310f649be29ffac0f04ca50a0bd0ed9a3352",
    "fecha": "2022-06-28",
    "comercio": "TOTAL PLAY",
    "giro_comercio": "SERVICIOS DE TELECOMUNICACION, LLAMADAS LOC Y LARG",
    "tipo_venta": "digital",
    "monto": 98.93
  },
  {
    "id": "c548310f649be29ffac0f04ca50a0bd0ed9a3352",
    "fecha": "2022-07-11",
    "comercio": "AMAZON",
    "giro_comercio": "COMERCIOS ELECTRONICOS (VTAS POR INTERNET)",
    "tipo_venta": "digital",
    "monto": 5.99
  },
  {
    "id": "c548310f649be29ffac0f04ca50a0bd0ed9a3352",
    "fecha": "2022-07-11",
    "comercio": "TOTAL PLAY",
    "giro_comercio": "SERVICIOS DE TELECOMUNICACION, LLAMADAS LOC Y LARG",
    "tipo_venta": "digital",
    "monto": 93.18
  },
  {
    "id": "c548310f649be29ffac0f04ca50a0bd0ed9a3352",
    "fecha": "2022-07-16",
    "comercio": "RENTAMOVISTAR",
    "giro_comercio": "AGREGADOR",
    "tipo_venta": "digital",
    "monto": 32.29
  },
  {
    "id": "c548310f649be29ffac0f04ca50a0bd0ed9a3352",
    "fecha": "2022-07-16",
    "comercio": "TELEFONICA",
    "giro_comercio": "SERVICIOS DE TELECOMUNICACION, LLAMADAS LOC Y LARG",
    "tipo_venta": "digital",
    "monto": 32.29
  },
  {
    "id": "c548310f649be29ffac0f04ca50a0bd0ed9a3352",
    "fecha": "2022-07-22",
    "comercio": "TOTALPLAY",
    "giro_comercio": "SERVICIOS DE TELECOMUNICACION, LLAMADAS LOC Y LARG",
    "tipo_venta": "digital",
    "monto": 82.84
  },
  {
    "id": "c548310f649be29ffac0f04ca50a0bd0ed9a3352",
    "fecha": "2022-07-23",
    "comercio": "CFE",
    "giro_comercio": "SERV GUBERNAM, AGUA, ELECTRICIDAD,PREDIAL,TENENCIA",
    "tipo_venta": "digital",
    "monto": 177.39
  },
  {
    "id": "c548310f649be29ffac0f04ca50a0bd0ed9a3352",
    "fecha": "2022-07-25",
    "comercio": "CINEPOLIS",
    "giro_comercio": "AGREGADOR",
    "tipo_venta": "digital",
    "monto": 44.13
  },
  {
    "id": "c548310f649be29ffac0f04ca50a0bd0ed9a3352",
    "fecha": "2022-07-28",
    "comercio": "CINEPOLIS",
    "giro_comercio": "AGREGADOR",
    "tipo_venta": "digital",
    "monto": 48.61
  },
  {
    "id": "c548310f649be29ffac0f04ca50a0bd0ed9a3352",
    "fecha": "2022-07-28",
    "comercio": "CINEPOLIS",
    "giro_comercio": "AGREGADOR",
    "tipo_venta": "digital",
    "monto": 26.89
  },
  {
    "id": "c548310f649be29ffac0f04ca50a0bd0ed9a3352",
    "fecha": "2022-07-29",
    "comercio": "AMAZON",
    "giro_comercio": "COMERCIOS ELECTRONICOS (VTAS POR INTERNET)",
    "tipo_venta": "digital",
    "monto": 909.01
  },
  {
    "id": "c548310f649be29ffac0f04ca50a0bd0ed9a3352",
    "fecha": "2022-07-30",
    "comercio": "AMAZON",
    "giro_comercio": "COMERCIOS ELECTRONICOS (VTAS POR INTERNET)",
    "tipo_venta": "digital",
    "monto": 34.4
  },
  {
    "id": "c548310f649be29ffac0f04ca50a0bd0ed9a3352",
    "fecha": "2022-07-30",
    "comercio": "TELEFONICA",
    "giro_comercio": "SERVICIOS DE TELECOMUNICACION, LLAMADAS LOC Y LARG",
    "tipo_venta": "digital",
    "monto": 32.29
  },
  {
    "id": "c548310f649be29ffac0f04ca50a0bd0ed9a3352",
    "fecha": "2022-07-31",
    "comercio": "AMAZON",
    "giro_comercio": "COMERCIOS ELECTRONICOS (VTAS POR INTERNET)",
    "tipo_venta": "digital",
    "monto": 44.47
  },
  {
    "id": "c548310f649be29ffac0f04ca50a0bd0ed9a3352",
    "fecha": "2022-08-03",
    "comercio": "AMAZON",
    "giro_comercio": "COMERCIOS ELECTRONICOS (VTAS POR INTERNET)",
    "tipo_venta": "digital",
    "monto": 91.34
  },
  {
    "id": "c548310f649be29ffac0f04ca50a0bd0ed9a3352",
    "fecha": "2022-08-07",
    "comercio": "FARMACIAS DEL AHORRO",
    "giro_comercio": "DROGUERIAS, (FARMACIAS)",
    "tipo_venta": "fisica",
    "monto": 305.48
  },
  {
    "id": "c548310f649be29ffac0f04ca50a0bd0ed9a3352",
    "fecha": "2022-08-11",
    "comercio": "AMAZON",
    "giro_comercio": "COMERCIOS ELECTRONICOS (VTAS POR INTERNET)",
    "tipo_venta": "digital",
    "monto": 5.99
  },
  {
    "id": "c548310f649be29ffac0f04ca50a0bd0ed9a3352",
    "fecha": "2022-08-11",
    "comercio": "TOTAL PLAY",
    "giro_comercio": "SERVICIOS DE TELECOMUNICACION, LLAMADAS LOC Y LARG",
    "tipo_venta": "digital",
    "monto": 93.18
  },
  {
    "id": "c548310f649be29ffac0f04ca50a0bd0ed9a3352",
    "fecha": "2022-08-12",
    "comercio": "MICROSOFT",
    "giro_comercio": "AGREGADOR",
    "tipo_venta": "digital",
    "monto": 4.72
  },
  {
    "id": "c548310f649be29ffac0f04ca50a0bd0ed9a3352",
    "fecha": "2022-08-14",
    "comercio": "CFE",
    "giro_comercio": "SERV GUBERNAM, AGUA, ELECTRICIDAD,PREDIAL,TENENCIA",
    "tipo_venta": "digital",
    "monto": 18.97
  },
  {
    "id": "c548310f649be29ffac0f04ca50a0bd0ed9a3352",
    "fecha": "2022-08-14",
    "comercio": "CFE",
    "giro_comercio": "SERV GUBERNAM, AGUA, ELECTRICIDAD,PREDIAL,TENENCIA",
    "tipo_venta": "digital",
    "monto": 20.35
  },
  {
    "id": "c548310f649be29ffac0f04ca50a0bd0ed9a3352",
    "fecha": "2022-08-21",
    "comercio": "RAPPI",
    "giro_comercio": "AGREGADOR",
    "tipo_venta": "digital",
    "monto": 14.02
  },
  {
    "id": "c548310f649be29ffac0f04ca50a0bd0ed9a3352",
    "fecha": "2022-08-26",
    "comercio": "FARMACIAS DEL AHORRO",
    "giro_comercio": "AGREGADOR",
    "tipo_venta": "digital",
    "monto": 195.43
  },
  {
    "id": "c548310f649be29ffac0f04ca50a0bd0ed9a3352",
    "fecha": "2022-08-26",
    "comercio": "FARMACIAS DEL AHORRO",
    "giro_comercio": "AGREGADOR",
    "tipo_venta": "digital",
    "monto": 195.43
  },
  {
    "id": "c548310f649be29ffac0f04ca50a0bd0ed9a3352",
    "fecha": "2022-08-26",
    "comercio": "AMAZON",
    "giro_comercio": "COMERCIOS ELECTRONICOS (VTAS POR INTERNET)",
    "tipo_venta": "digital",
    "monto": 29.95
  },
  {
    "id": "c548310f649be29ffac0f04ca50a0bd0ed9a3352",
    "fecha": "2022-08-27",
    "comercio": "AMAZON",
    "giro_comercio": "COMERCIOS ELECTRONICOS (VTAS POR INTERNET)",
    "tipo_venta": "digital",
    "monto": 244.63
  },
  {
    "id": "c548310f649be29ffac0f04ca50a0bd0ed9a3352",
    "fecha": "2022-08-27",
    "comercio": "RAPPI",
    "giro_comercio": "AGREGADOR",
    "tipo_venta": "digital",
    "monto": 11.27
  },
  {
    "id": "c548310f649be29ffac0f04ca50a0bd0ed9a3352",
    "fecha": "2022-08-29",
    "comercio": "AMAZON",
    "giro_comercio": "COMERCIOS ELECTRONICOS (VTAS POR INTERNET)",
    "tipo_venta": "digital",
    "monto": 29.95
  },
  {
    "id": "c548310f649be29ffac0f04ca50a0bd0ed9a3352",
    "fecha": "2022-08-29",
    "comercio": "AMAZON",
    "giro_comercio": "COMERCIOS ELECTRONICOS (VTAS POR INTERNET)",
    "tipo_venta": "digital",
    "monto": 29.95
  },
  {
    "id": "c548310f649be29ffac0f04ca50a0bd0ed9a3352",
    "fecha": "2022-08-29",
    "comercio": "AMAZON",
    "giro_comercio": "COMERCIOS ELECTRONICOS (VTAS POR INTERNET)",
    "tipo_venta": "digital",
    "monto": 12.76
  },
  {
    "id": "c548310f649be29ffac0f04ca50a0bd0ed9a3352",
    "fecha": "2022-08-30",
    "comercio": "CINEPOLIS",
    "giro_comercio": "AGREGADOR",
    "tipo_venta": "digital",
    "monto": 80.2
  },
  {
    "id": "c548310f649be29ffac0f04ca50a0bd0ed9a3352",
    "fecha": "2022-08-30",
    "comercio": "TELEFONICA",
    "giro_comercio": "SERVICIOS DE TELECOMUNICACION, LLAMADAS LOC Y LARG",
    "tipo_venta": "digital",
    "monto": 32.29
  },
  {
    "id": "c548310f649be29ffac0f04ca50a0bd0ed9a3352",
    "fecha": "2022-08-31",
    "comercio": "RAPPI",
    "giro_comercio": "AGREGADOR",
    "tipo_venta": "digital",
    "monto": 12.41
  },
  {
    "id": "c548310f649be29ffac0f04ca50a0bd0ed9a3352",
    "fecha": "2022-09-10",
    "comercio": "TOTALPLAY",
    "giro_comercio": "SERVICIOS DE TELECOMUNICACION, LLAMADAS LOC Y LARG",
    "tipo_venta": "digital",
    "monto": 88.59
  },
  {
    "id": "c548310f649be29ffac0f04ca50a0bd0ed9a3352",
    "fecha": "2022-09-11",
    "comercio": "AMAZON",
    "giro_comercio": "COMERCIOS ELECTRONICOS (VTAS POR INTERNET)",
    "tipo_venta": "digital",
    "monto": 5.99
  },
  {
    "id": "c548310f649be29ffac0f04ca50a0bd0ed9a3352",
    "fecha": "2022-09-11",
    "comercio": "TOTAL PLAY",
    "giro_comercio": "SERVICIOS DE TELECOMUNICACION, LLAMADAS LOC Y LARG",
    "tipo_venta": "digital",
    "monto": 93.18
  },
  {
    "id": "c548310f649be29ffac0f04ca50a0bd0ed9a3352",
    "fecha": "2022-09-11",
    "comercio": "RAPPI",
    "giro_comercio": "AGREGADOR",
    "tipo_venta": "digital",
    "monto": 18.96
  },
  {
    "id": "c548310f649be29ffac0f04ca50a0bd0ed9a3352",
    "fecha": "2022-09-11",
    "comercio": "FARMACIAS GUADALAJARA",
    "giro_comercio": "DROGUERIAS, (FARMACIAS)",
    "tipo_venta": "fisica",
    "monto": 112.82
  },
  {
    "id": "c548310f649be29ffac0f04ca50a0bd0ed9a3352",
    "fecha": "2022-09-12",
    "comercio": "MICROSOFT",
    "giro_comercio": "AGREGADOR",
    "tipo_venta": "digital",
    "monto": 4.72
  },
  {
    "id": "c548310f649be29ffac0f04ca50a0bd0ed9a3352",
    "fecha": "2022-09-12",
    "comercio": "AMAZON",
    "giro_comercio": "COMERCIOS ELECTRONICOS (VTAS POR INTERNET)",
    "tipo_venta": "digital",
    "monto": 74.6
  },
  {
    "id": "c548310f649be29ffac0f04ca50a0bd0ed9a3352",
    "fecha": "2022-09-13",
    "comercio": "FARMACIAS DEL AHORRO",
    "giro_comercio": "AGREGADOR",
    "tipo_venta": "digital",
    "monto": 42.29
  },
  {
    "id": "c548310f649be29ffac0f04ca50a0bd0ed9a3352",
    "fecha": "2022-09-18",
    "comercio": "MERCADO PAGO",
    "giro_comercio": "MERCADO DIRECTO - VENTAS POR CATALOGO",
    "tipo_venta": "digital",
    "monto": 184.05
  },
  {
    "id": "c548310f649be29ffac0f04ca50a0bd0ed9a3352",
    "fecha": "2022-09-18",
    "comercio": "MERCADO PAGO",
    "giro_comercio": "MERCADO DIRECTO - VENTAS POR CATALOGO",
    "tipo_venta": "digital",
    "monto": 184.05
  },
  {
    "id": "c548310f649be29ffac0f04ca50a0bd0ed9a3352",
    "fecha": "2022-09-18",
    "comercio": "MERCADO PAGO",
    "giro_comercio": "MERCADEO DIRECTO - NO CLASIFICADO",
    "tipo_venta": "digital",
    "monto": 184.05
  },
  {
    "id": "c548310f649be29ffac0f04ca50a0bd0ed9a3352",
    "fecha": "2022-09-18",
    "comercio": "MERCADO PAGO",
    "giro_comercio": "MERCADO DIRECTO - VENTAS POR CATALOGO",
    "tipo_venta": "digital",
    "monto": 184.05
  },
  {
    "id": "c548310f649be29ffac0f04ca50a0bd0ed9a3352",
    "fecha": "2022-09-22",
    "comercio": "ITUNES",
    "giro_comercio": "AGREGADOR",
    "tipo_venta": "digital",
    "monto": 28.85
  },
  {
    "id": "c548310f649be29ffac0f04ca50a0bd0ed9a3352",
    "fecha": "2022-09-23",
    "comercio": "TOTALPLAY",
    "giro_comercio": "SERVICIOS DE TELECOMUNICACION, LLAMADAS LOC Y LARG",
    "tipo_venta": "digital",
    "monto": 82.84
  },
  {
    "id": "c548310f649be29ffac0f04ca50a0bd0ed9a3352",
    "fecha": "2022-09-23",
    "comercio": "WALMART",
    "giro_comercio": "AGREGADOR",
    "tipo_venta": "digital",
    "monto": 54.91
  },
  {
    "id": "c548310f649be29ffac0f04ca50a0bd0ed9a3352",
    "fecha": "2022-09-24",
    "comercio": "CFE",
    "giro_comercio": "SERV GUBERNAM, AGUA, ELECTRICIDAD,PREDIAL,TENENCIA",
    "tipo_venta": "digital",
    "monto": 177.5
  },
  {
    "id": "c548310f649be29ffac0f04ca50a0bd0ed9a3352",
    "fecha": "2022-09-28",
    "comercio": "CFE",
    "giro_comercio": "SERV GUBERNAM, AGUA, ELECTRICIDAD,PREDIAL,TENENCIA",
    "tipo_venta": "digital",
    "monto": 177.5
  },
  {
    "id": "c548310f649be29ffac0f04ca50a0bd0ed9a3352",
    "fecha": "2022-09-30",
    "comercio": "RENTAMOVISTAR",
    "giro_comercio": "AGREGADOR",
    "tipo_venta": "digital",
    "monto": 32.29
  },
  {
    "id": "c548310f649be29ffac0f04ca50a0bd0ed9a3352",
    "fecha": "2022-10-05",
    "comercio": "ITUNES",
    "giro_comercio": "AGREGADOR",
    "tipo_venta": "digital",
    "monto": 38.04
  },
  {
    "id": "c548310f649be29ffac0f04ca50a0bd0ed9a3352",
    "fecha": "2022-10-10",
    "comercio": "COSTCO",
    "giro_comercio": "CLUBES DE MAYORISTA",
    "tipo_venta": "fisica",
    "monto": 143.39
  },
  {
    "id": "c548310f649be29ffac0f04ca50a0bd0ed9a3352",
    "fecha": "2022-10-10",
    "comercio": "LIVERPOOL",
    "giro_comercio": "TIENDA DEPARTAMENTAL",
    "tipo_venta": "fisica",
    "monto": 37.16
  },
  {
    "id": "c548310f649be29ffac0f04ca50a0bd0ed9a3352",
    "fecha": "2022-10-11",
    "comercio": "AMAZON",
    "giro_comercio": "COMERCIOS ELECTRONICOS (VTAS POR INTERNET)",
    "tipo_venta": "digital",
    "monto": 5.99
  },
  {
    "id": "c548310f649be29ffac0f04ca50a0bd0ed9a3352",
    "fecha": "2022-10-11",
    "comercio": "TOTAL PLAY",
    "giro_comercio": "SERVICIOS DE TELECOMUNICACION, LLAMADAS LOC Y LARG",
    "tipo_venta": "digital",
    "monto": 93.18
  },
  {
    "id": "c548310f649be29ffac0f04ca50a0bd0ed9a3352",
    "fecha": "2022-10-11",
    "comercio": "WALMART",
    "giro_comercio": "AUTOSERVICIOS Y SUPERMERCADOS",
    "tipo_venta": "digital",
    "monto": 61.01
  },
  {
    "id": "c548310f649be29ffac0f04ca50a0bd0ed9a3352",
    "fecha": "2022-10-11",
    "comercio": "FARMACIAS GUADALAJARA",
    "giro_comercio": "DROGUERIAS, (FARMACIAS)",
    "tipo_venta": "fisica",
    "monto": 119.48
  },
  {
    "id": "c548310f649be29ffac0f04ca50a0bd0ed9a3352",
    "fecha": "2022-10-11",
    "comercio": "MICROSOFT",
    "giro_comercio": "AGREGADOR",
    "tipo_venta": "digital",
    "monto": 4.72
  },
  {
    "id": "c548310f649be29ffac0f04ca50a0bd0ed9a3352",
    "fecha": "2022-10-16",
    "comercio": "ITUNES",
    "giro_comercio": "AGREGADOR",
    "tipo_venta": "digital",
    "monto": 5.99
  },
  {
    "id": "c548310f649be29ffac0f04ca50a0bd0ed9a3352",
    "fecha": "2022-10-17",
    "comercio": "CINEPOLIS",
    "giro_comercio": "AGREGADOR",
    "tipo_venta": "digital",
    "monto": 40.22
  },
  {
    "id": "c548310f649be29ffac0f04ca50a0bd0ed9a3352",
    "fecha": "2022-10-17",
    "comercio": "CINEPOLIS",
    "giro_comercio": "AGREGADOR",
    "tipo_venta": "digital",
    "monto": 38.04
  },
  {
    "id": "c548310f649be29ffac0f04ca50a0bd0ed9a3352",
    "fecha": "2022-10-19",
    "comercio": "CFE",
    "giro_comercio": "SERV GUBERNAM, AGUA, ELECTRICIDAD,PREDIAL,TENENCIA",
    "tipo_venta": "digital",
    "monto": 11.96
  },
  {
    "id": "c548310f649be29ffac0f04ca50a0bd0ed9a3352",
    "fecha": "2022-10-19",
    "comercio": "CFE",
    "giro_comercio": "SERV GUBERNAM, AGUA, ELECTRICIDAD,PREDIAL,TENENCIA",
    "tipo_venta": "digital",
    "monto": 20.69
  },
  {
    "id": "c548310f649be29ffac0f04ca50a0bd0ed9a3352",
    "fecha": "2022-10-19",
    "comercio": "MERCADO PAGO",
    "giro_comercio": "MERCADO DIRECTO - VENTAS POR CATALOGO",
    "tipo_venta": "digital",
    "monto": 77.29
  },
  {
    "id": "c548310f649be29ffac0f04ca50a0bd0ed9a3352",
    "fecha": "2022-10-23",
    "comercio": "RAPPI",
    "giro_comercio": "AGREGADOR",
    "tipo_venta": "digital",
    "monto": 18.61
  },
  {
    "id": "c548310f649be29ffac0f04ca50a0bd0ed9a3352",
    "fecha": "2022-10-23",
    "comercio": "RAPPI",
    "giro_comercio": "AGREGADOR",
    "tipo_venta": "digital",
    "monto": 7.71
  },
  {
    "id": "c548310f649be29ffac0f04ca50a0bd0ed9a3352",
    "fecha": "2022-10-25",
    "comercio": "UBRPAGOSMEX",
    "giro_comercio": "AGREGADOR",
    "tipo_venta": "digital",
    "monto": 8.28
  },
  {
    "id": "c548310f649be29ffac0f04ca50a0bd0ed9a3352",
    "fecha": "2022-10-25",
    "comercio": "UBRPAGOSMEX",
    "giro_comercio": "AGREGADOR",
    "tipo_venta": "digital",
    "monto": 27.0
  },
  {
    "id": "c548310f649be29ffac0f04ca50a0bd0ed9a3352",
    "fecha": "2022-10-26",
    "comercio": "RAPPI",
    "giro_comercio": "AGREGADOR",
    "tipo_venta": "digital",
    "monto": 51.73
  },
  {
    "id": "c548310f649be29ffac0f04ca50a0bd0ed9a3352",
    "fecha": "2022-10-26",
    "comercio": "UBRPAGOSMEX",
    "giro_comercio": "AGREGADOR",
    "tipo_venta": "digital",
    "monto": 19.76
  },
  {
    "id": "c548310f649be29ffac0f04ca50a0bd0ed9a3352",
    "fecha": "2022-10-26",
    "comercio": "UBRPAGOSMEX",
    "giro_comercio": "AGREGADOR",
    "tipo_venta": "digital",
    "monto": 23.21
  },
  {
    "id": "c548310f649be29ffac0f04ca50a0bd0ed9a3352",
    "fecha": "2022-10-27",
    "comercio": "UBRPAGOSMEX",
    "giro_comercio": "AGREGADOR",
    "tipo_venta": "digital",
    "monto": 38.15
  },
  {
    "id": "c548310f649be29ffac0f04ca50a0bd0ed9a3352",
    "fecha": "2022-10-30",
    "comercio": "WALMART",
    "giro_comercio": "AGREGADOR",
    "tipo_venta": "digital",
    "monto": 106.28
  },
  {
    "id": "c548310f649be29ffac0f04ca50a0bd0ed9a3352",
    "fecha": "2022-10-30",
    "comercio": "TOTALPLAY",
    "giro_comercio": "SERVICIOS DE TELECOMUNICACION, LLAMADAS LOC Y LARG",
    "tipo_venta": "digital",
    "monto": 82.84
  },
  {
    "id": "c548310f649be29ffac0f04ca50a0bd0ed9a3352",
    "fecha": "2022-10-30",
    "comercio": "RENTAMOVISTAR",
    "giro_comercio": "AGREGADOR",
    "tipo_venta": "digital",
    "monto": 32.29
  },
  {
    "id": "c548310f649be29ffac0f04ca50a0bd0ed9a3352",
    "fecha": "2022-11-04",
    "comercio": "CINEPOLIS",
    "giro_comercio": "AGREGADOR",
    "tipo_venta": "digital",
    "monto": 40.22
  },
  {
    "id": "c548310f649be29ffac0f04ca50a0bd0ed9a3352",
    "fecha": "2022-11-05",
    "comercio": "ITUNES",
    "giro_comercio": "AGREGADOR",
    "tipo_venta": "digital",
    "monto": 38.04
  },
  {
    "id": "c548310f649be29ffac0f04ca50a0bd0ed9a3352",
    "fecha": "2022-11-09",
    "comercio": "RAPPI",
    "giro_comercio": "AGREGADOR",
    "tipo_venta": "digital",
    "monto": 8.92
  },
  {
    "id": "c548310f649be29ffac0f04ca50a0bd0ed9a3352",
    "fecha": "2022-11-11",
    "comercio": "AMAZON",
    "giro_comercio": "COMERCIOS ELECTRONICOS (VTAS POR INTERNET)",
    "tipo_venta": "digital",
    "monto": 5.99
  },
  {
    "id": "c548310f649be29ffac0f04ca50a0bd0ed9a3352",
    "fecha": "2022-11-11",
    "comercio": "TOTAL PLAY",
    "giro_comercio": "SERVICIOS DE TELECOMUNICACION, LLAMADAS LOC Y LARG",
    "tipo_venta": "digital",
    "monto": 93.18
  },
  {
    "id": "c548310f649be29ffac0f04ca50a0bd0ed9a3352",
    "fecha": "2022-11-11",
    "comercio": "RAPPI",
    "giro_comercio": "AGREGADOR",
    "tipo_venta": "digital",
    "monto": 15.3
  },
  {
    "id": "c548310f649be29ffac0f04ca50a0bd0ed9a3352",
    "fecha": "2022-11-11",
    "comercio": "MICROSOFT",
    "giro_comercio": "AGREGADOR",
    "tipo_venta": "digital",
    "monto": 4.72
  },
  {
    "id": "c548310f649be29ffac0f04ca50a0bd0ed9a3352",
    "fecha": "2022-11-12",
    "comercio": "RAPPI",
    "giro_comercio": "AGREGADOR",
    "tipo_venta": "digital",
    "monto": 15.76
  },
  {
    "id": "c548310f649be29ffac0f04ca50a0bd0ed9a3352",
    "fecha": "2022-11-13",
    "comercio": "WALMART",
    "giro_comercio": "AGREGADOR",
    "tipo_venta": "digital",
    "monto": 79.85
  },
  {
    "id": "c548310f649be29ffac0f04ca50a0bd0ed9a3352",
    "fecha": "2022-11-13",
    "comercio": "RAPPI",
    "giro_comercio": "AGREGADOR",
    "tipo_venta": "digital",
    "monto": 18.7
  },
  {
    "id": "c548310f649be29ffac0f04ca50a0bd0ed9a3352",
    "fecha": "2022-11-15",
    "comercio": "CFE",
    "giro_comercio": "SERV GUBERNAM, AGUA, ELECTRICIDAD,PREDIAL,TENENCIA",
    "tipo_venta": "digital",
    "monto": 173.83
  },
  {
    "id": "c548310f649be29ffac0f04ca50a0bd0ed9a3352",
    "fecha": "2022-11-15",
    "comercio": "RAPPI",
    "giro_comercio": "AGREGADOR",
    "tipo_venta": "digital",
    "monto": 48.89
  },
  {
    "id": "c548310f649be29ffac0f04ca50a0bd0ed9a3352",
    "fecha": "2022-11-17",
    "comercio": "AMAZON",
    "giro_comercio": "COMERCIOS ELECTRONICOS (VTAS POR INTERNET)",
    "tipo_venta": "digital",
    "monto": 216.01
  },
  {
    "id": "c548310f649be29ffac0f04ca50a0bd0ed9a3352",
    "fecha": "2022-11-22",
    "comercio": "TOTALPLAY",
    "giro_comercio": "SERVICIOS DE TELECOMUNICACION, LLAMADAS LOC Y LARG",
    "tipo_venta": "digital",
    "monto": 82.84
  },
  {
    "id": "c548310f649be29ffac0f04ca50a0bd0ed9a3352",
    "fecha": "2022-12-04",
    "comercio": "RENTAMOVISTAR",
    "giro_comercio": "AGREGADOR",
    "tipo_venta": "digital",
    "monto": 32.29
  },
  {
    "id": "c548310f649be29ffac0f04ca50a0bd0ed9a3352",
    "fecha": "2022-12-09",
    "comercio": "CFE",
    "giro_comercio": "SERV GUBERNAM, AGUA, ELECTRICIDAD,PREDIAL,TENENCIA",
    "tipo_venta": "digital",
    "monto": 15.98
  },
  {
    "id": "c548310f649be29ffac0f04ca50a0bd0ed9a3352",
    "fecha": "2022-12-09",
    "comercio": "CFE",
    "giro_comercio": "SERV GUBERNAM, AGUA, ELECTRICIDAD,PREDIAL,TENENCIA",
    "tipo_venta": "digital",
    "monto": 16.55
  },
  {
    "id": "c548310f649be29ffac0f04ca50a0bd0ed9a3352",
    "fecha": "2022-12-10",
    "comercio": "WALMART",
    "giro_comercio": "AGREGADOR",
    "tipo_venta": "digital",
    "monto": 123.45
  },
  {
    "id": "c548310f649be29ffac0f04ca50a0bd0ed9a3352",
    "fecha": "2022-12-11",
    "comercio": "AMAZON",
    "giro_comercio": "COMERCIOS ELECTRONICOS (VTAS POR INTERNET)",
    "tipo_venta": "digital",
    "monto": 5.99
  },
  {
    "id": "c548310f649be29ffac0f04ca50a0bd0ed9a3352",
    "fecha": "2022-12-11",
    "comercio": "TOTAL PLAY",
    "giro_comercio": "SERVICIOS DE TELECOMUNICACION, LLAMADAS LOC Y LARG",
    "tipo_venta": "digital",
    "monto": 93.18
  },
  {
    "id": "c548310f649be29ffac0f04ca50a0bd0ed9a3352",
    "fecha": "2022-12-16",
    "comercio": "AMAZON",
    "giro_comercio": "COMERCIOS ELECTRONICOS (VTAS POR INTERNET)",
    "tipo_venta": "digital",
    "monto": 60.21
  },
  {
    "id": "c548310f649be29ffac0f04ca50a0bd0ed9a3352",
    "fecha": "2022-12-16",
    "comercio": "AMAZON",
    "giro_comercio": "COMERCIOS ELECTRONICOS (VTAS POR INTERNET)",
    "tipo_venta": "digital",
    "monto": 18.62
  },
  {
    "id": "c548310f649be29ffac0f04ca50a0bd0ed9a3352",
    "fecha": "2022-12-17",
    "comercio": "AMAZON",
    "giro_comercio": "COMERCIOS ELECTRONICOS (VTAS POR INTERNET)",
    "tipo_venta": "digital",
    "monto": 20.81
  },
  {
    "id": "c548310f649be29ffac0f04ca50a0bd0ed9a3352",
    "fecha": "2022-12-21",
    "comercio": "AMAZON",
    "giro_comercio": "COMERCIOS ELECTRONICOS (VTAS POR INTERNET)",
    "tipo_venta": "digital",
    "monto": 88.25
  },
  {
    "id": "c548310f649be29ffac0f04ca50a0bd0ed9a3352",
    "fecha": "2022-12-21",
    "comercio": "AMAZON",
    "giro_comercio": "COMERCIOS ELECTRONICOS (VTAS POR INTERNET)",
    "tipo_venta": "digital",
    "monto": 64.4
  },
  {
    "id": "c548310f649be29ffac0f04ca50a0bd0ed9a3352",
    "fecha": "2022-12-23",
    "comercio": "TOTALPLAY",
    "giro_comercio": "SERVICIOS DE TELECOMUNICACION, LLAMADAS LOC Y LARG",
    "tipo_venta": "digital",
    "monto": 82.84
  },
  {
    "id": "c548310f649be29ffac0f04ca50a0bd0ed9a3352",
    "fecha": "2022-12-30",
    "comercio": "APPLE",
    "giro_comercio": "COMPUTADORAS EQUIPO PERIF DE COMPUTADORAS SOFTWARE",
    "tipo_venta": "digital",
    "monto": 379.24
  },
  {
    "id": "c548310f649be29ffac0f04ca50a0bd0ed9a3352",
    "fecha": "2022-12-31",
    "comercio": "CFE",
    "giro_comercio": "SERV GUBERNAM, AGUA, ELECTRICIDAD,PREDIAL,TENENCIA",
    "tipo_venta": "digital",
    "monto": 11.62
  },
  {
    "id": "c548310f649be29ffac0f04ca50a0bd0ed9a3352",
    "fecha": "2022-12-31",
    "comercio": "CFE",
    "giro_comercio": "SERV GUBERNAM, AGUA, ELECTRICIDAD,PREDIAL,TENENCIA",
    "tipo_venta": "digital",
    "monto": 131.78
  },
  {
    "id": "c548310f649be29ffac0f04ca50a0bd0ed9a3352",
    "fecha": "2023-01-03",
    "comercio": "WALMART",
    "giro_comercio": "AGREGADOR",
    "tipo_venta": "digital",
    "monto": 130.75
  },
  {
    "id": "c548310f649be29ffac0f04ca50a0bd0ed9a3352",
    "fecha": "2023-01-03",
    "comercio": "AMAZON",
    "giro_comercio": "COMERCIOS ELECTRONICOS (VTAS POR INTERNET)",
    "tipo_venta": "digital",
    "monto": 41.7
  },
  {
    "id": "c548310f649be29ffac0f04ca50a0bd0ed9a3352",
    "fecha": "2023-01-07",
    "comercio": "RAPPI",
    "giro_comercio": "AGREGADOR",
    "tipo_venta": "digital",
    "monto": 24.01
  },
  {
    "id": "c548310f649be29ffac0f04ca50a0bd0ed9a3352",
    "fecha": "2023-01-08",
    "comercio": "TELEFONICA",
    "giro_comercio": "SERVICIOS DE TELECOMUNICACION, LLAMADAS LOC Y LARG",
    "tipo_venta": "digital",
    "monto": 32.29
  },
  {
    "id": "c548310f649be29ffac0f04ca50a0bd0ed9a3352",
    "fecha": "2023-01-11",
    "comercio": "AMAZON",
    "giro_comercio": "COMERCIOS ELECTRONICOS (VTAS POR INTERNET)",
    "tipo_venta": "digital",
    "monto": 5.99
  },
  {
    "id": "c548310f649be29ffac0f04ca50a0bd0ed9a3352",
    "fecha": "2023-01-11",
    "comercio": "CINEPOLIS",
    "giro_comercio": "CINES, TEATROS",
    "tipo_venta": "digital",
    "monto": 40.22
  },
  {
    "id": "c548310f649be29ffac0f04ca50a0bd0ed9a3352",
    "fecha": "2023-01-11",
    "comercio": "CINEPOLIS",
    "giro_comercio": "CINES, TEATROS",
    "tipo_venta": "digital",
    "monto": 23.68
  },
  {
    "id": "c548310f649be29ffac0f04ca50a0bd0ed9a3352",
    "fecha": "2023-01-11",
    "comercio": "MICROSOFT",
    "giro_comercio": "AGREGADOR",
    "tipo_venta": "digital",
    "monto": 4.72
  },
  {
    "id": "c548310f649be29ffac0f04ca50a0bd0ed9a3352",
    "fecha": "2023-01-12",
    "comercio": "AMAZON",
    "giro_comercio": "COMERCIOS ELECTRONICOS (VTAS POR INTERNET)",
    "tipo_venta": "digital",
    "monto": 26.66
  },
  {
    "id": "c548310f649be29ffac0f04ca50a0bd0ed9a3352",
    "fecha": "2023-01-12",
    "comercio": "FARMACIAS DEL AHORRO",
    "giro_comercio": "DROGUERIAS, (FARMACIAS)",
    "tipo_venta": "fisica",
    "monto": 167.05
  },
  {
    "id": "c548310f649be29ffac0f04ca50a0bd0ed9a3352",
    "fecha": "2023-01-12",
    "comercio": "FARMACIAS DEL AHORRO",
    "giro_comercio": "DROGUERIAS, (FARMACIAS)",
    "tipo_venta": "fisica",
    "monto": 167.05
  },
  {
    "id": "c548310f649be29ffac0f04ca50a0bd0ed9a3352",
    "fecha": "2023-01-13",
    "comercio": "AMAZON",
    "giro_comercio": "COMERCIOS ELECTRONICOS (VTAS POR INTERNET)",
    "tipo_venta": "digital",
    "monto": 172.45
  },
  {
    "id": "c548310f649be29ffac0f04ca50a0bd0ed9a3352",
    "fecha": "2023-01-16",
    "comercio": "TELCEL",
    "giro_comercio": "SERVICIOS EMPRESARIALES - NO CLASIFICADOS",
    "tipo_venta": "digital",
    "monto": 11.73
  },
  {
    "id": "c548310f649be29ffac0f04ca50a0bd0ed9a3352",
    "fecha": "2023-01-17",
    "comercio": "MERCADO PAGO",
    "giro_comercio": "COMERCIOS ELECTRONICOS (VTAS POR INTERNET)",
    "tipo_venta": "digital",
    "monto": 172.33
  },
  {
    "id": "c548310f649be29ffac0f04ca50a0bd0ed9a3352",
    "fecha": "2023-01-18",
    "comercio": "CFE",
    "giro_comercio": "SERV GUBERNAM, AGUA, ELECTRICIDAD,PREDIAL,TENENCIA",
    "tipo_venta": "digital",
    "monto": 219.67
  },
  {
    "id": "c548310f649be29ffac0f04ca50a0bd0ed9a3352",
    "fecha": "2023-01-20",
    "comercio": "TELCEL",
    "giro_comercio": "SERVICIOS DE TELECOMUNICACION, LLAMADAS LOC Y LARG",
    "tipo_venta": "digital",
    "monto": 9.43
  },
  {
    "id": "c548310f649be29ffac0f04ca50a0bd0ed9a3352",
    "fecha": "2023-01-21",
    "comercio": "AMAZON",
    "giro_comercio": "COMERCIOS ELECTRONICOS (VTAS POR INTERNET)",
    "tipo_venta": "digital",
    "monto": 36.89
  },
  {
    "id": "c548310f649be29ffac0f04ca50a0bd0ed9a3352",
    "fecha": "2023-01-21",
    "comercio": "RAPPI",
    "giro_comercio": "AGREGADOR",
    "tipo_venta": "digital",
    "monto": 78.05
  },
  {
    "id": "c548310f649be29ffac0f04ca50a0bd0ed9a3352",
    "fecha": "2023-01-24",
    "comercio": "WALMART",
    "giro_comercio": "AGREGADOR",
    "tipo_venta": "digital",
    "monto": 104.67
  },
  {
    "id": "c548310f649be29ffac0f04ca50a0bd0ed9a3352",
    "fecha": "2023-01-29",
    "comercio": "RAPPI",
    "giro_comercio": "AGREGADOR",
    "tipo_venta": "digital",
    "monto": 16.89
  }
]